Workbook

Sheet Read me
B2: Australia dataset, for checking
B3: 45 programmes across the 8 Group of Eight universities, plus a 23 step student visa chain. Everything was web-checked on 13 September 2026 and every record already carries a source link and a quote from the page.
B6: What to do | C6: Work down the 'Check first' tab. It is sorted so the things that are visibly wrong on the site come before the things that are merely thin. Tick the Done column as you go and the counter at the top updates itself.
B8: Red rows | C8: Wrong on the page right now. Eight records. Half an hour.
B9: Amber rows | C9: Fields Germany fills on every record and Australia fills on none. They are answered once per university on the Institutions tab, not once per programme, so it is 8 cities and 8 homepages rather than 90 cells.
B10: Blue rows | C10: Judgement calls. Each is defensible as it stands. Read the ask column and decide.
B12: Already clean | C12: No stray line breaks, no double spaces, no smart quotes, no placeholder text, no duplicate programmes, no gaps in the record numbering, and every one of the 45 records has a quote of 67 characters or more. None of that needs re-checking.
B14: On the links | C14: Automated checking cannot confirm these. Melbourne, Monash and UQ block scripted requests, which is why 30 of the 90 URLs answered 403 or timed out to a robot. That is the university's bot filter, not a dead link. Opening them in a browser is the only check that means anything, which is what the 'Link never marked as opening' rows are for.
B16: On coverage | C16: Every record here is Group of Eight. That is a deliberate top end rather than a cross-section: no Australian Technology Network, no regional universities, and Adelaide University is included post-merger. Worth deciding whether the file claims to cover Australia or to cover the Go8.
B18: Sending edits back | C18: Edit in place on the Programmes tab. Keep the record_id column untouched, since that is what the import matches on.

Sheet Check first
A1: Done | B1: Of | D1: Red open / amber open / blue open
A2: =COUNTIF(A4:A113,"yes") | B2: =COUNTA(C4:C113) | D2: =COUNTIFS(B4:B113,1,A4:A113,"")&" red, "&COUNTIFS(B4:B113,2,A4:A113,"")&" amber, "&COUNTIFS(B4:B113,3,A4:A113,"")&" blue"
A3: Done | B3: Priority | C3: Record | D3: What is wrong | E3: Field | F3: What it says now | G3: What to do
B4: 1 | C4: AU-040 | D4: Degree name carries a comment | E4: degree | F4: Bachelor (Honours) — now titled Bachelor of Laws (Honours) | G4: Set it to 'Bachelor of Laws (Honours)' and move the rename into notes
B5: 1 | C5: AU-037 | D5: Institution name carries an editorial note, and that note is what the reader sees | E5: institution | F5: Adelaide University (merged University of Adelaide + UniSA; sheet listed University of Adelaide) | G5: Set the name to 'Adelaide University'. The merger belongs in notes, where it already is
B6: 1 | C6: AU-038 | D6: Institution name carries an editorial note, and that note is what the reader sees | E6: institution | F6: Adelaide University (merged University of Adelaide + UniSA; sheet listed University of Adelaide) | G6: Set the name to 'Adelaide University'. The merger belongs in notes, where it already is
B7: 1 | C7: AU-039 | D7: Institution name carries an editorial note, and that note is what the reader sees | E7: institution | F7: Adelaide University (merged University of Adelaide + UniSA; sheet listed University of Adelaide) | G7: Set the name to 'Adelaide University'. The merger belongs in notes, where it already is
B8: 1 | C8: AU-040 | D8: Institution name carries an editorial note, and that note is what the reader sees | E8: institution | F8: Adelaide University (merged University of Adelaide + UniSA; sheet listed University of Adelaide) | G8: Set the name to 'Adelaide University'. The merger belongs in notes, where it already is
B9: 1 | C9: AU-041 | D9: Institution name carries an editorial note, and that note is what the reader sees | E9: institution | F9: Adelaide University (merged University of Adelaide + UniSA; sheet listed University of Adelaide) | G9: Set the name to 'Adelaide University'. The merger belongs in notes, where it already is
B10: 1 | C10: AU-031 | D10: Source link has words after the URL, so it does not open | E10: source_url_you_used | F10: https://study.uq.edu.au/study-options/programs/bachelor-commerce-2336 (entry-requirements selector, S1 2027, India) | G10: Move everything after the URL into notes, leave the bare link
B11: 1 | C11: AU-032 | D11: Source link has words after the URL, so it does not open | E11: source_url_you_used | F11: https://study.uq.edu.au/study-options/programs/bachelor-business-management-2171 (entry-requirements selector, S1 2027, India) | G11: Move everything after the URL into notes, leave the bare link
B12: 1 | C12: AU-033 | D12: Source link has words after the URL, so it does not open | E12: source_url_you_used | F12: https://study.uq.edu.au/study-options/programs/bachelor-engineering-honours-2455 (entry-requirements selector, S1 2027, India) | G12: Move everything after the URL into notes, leave the bare link
B13: 1 | C13: AU-034 | D13: Source link has words after the URL, so it does not open | E13: source_url_you_used | F13: https://study.uq.edu.au/study-options/programs/bachelor-science-2461 (entry-requirements selector, S1 2027, India) | G13: Move everything after the URL into notes, leave the bare link
B14: 1 | C14: AU-035 | D14: Source link has words after the URL, so it does not open | E14: source_url_you_used | F14: https://study.uq.edu.au/study-options/programs/bachelor-laws-honours-2471 (entry-requirements selector, S1 2027, India) | G14: Move everything after the URL into notes, leave the bare link
B15: 1 | C15: AU-036 | D15: Source link has words after the URL, so it does not open | E15: source_url_you_used | F15: https://study.uq.edu.au/study-options/programs/bachelor-advanced-finance-and-economics-honours-2140 (entry-requirements selector, S1 2027, India) | G15: Move everything after the URL into notes, leave the bare link
... B113: 3 | C113: AU-036 | D113: Sortable deadline names a year the source sentence does not | E113: deadline_iso | F113: 2026-11-30 <- Semester 1 only: applications close 30 November of the previous year | G113: Confirm the year. The source says 'the year prior to commencement' without naming one

Sheet Programmes
A1: record_id (do not edit) | B1: institution | C1: city | D1: programme | E1: degree | F1: url | G1: institution type | H1: language | I1: years | J1: entry | K1: IB | L1: A Level | M1: CBSE | N1: ISC | O1: other | P1: English requirement | Q1: selection | R1: deadline | S1: tuition, international | T1: scholarships | U1: visa | V1: apply | W1: notes | X1: status | Y1: what the sheet got wrong | Z1: source URL | AA1: exact quote | AB1: date checked | AC1: link works | AD1: checked by | AE1: documents required | AF1: deadline rounds | AG1: fee year | AH1: application fee | AI1: deadline (sortable) | AJ1: India entry (combined)
A2: AU-001 | B2: University of Melbourne | C2: Australia | D2: Bachelor of Commerce | E2: Bachelor | F2: https://study.unimelb.edu.au/find/courses/undergraduate/bachelor-of-commerce/ | G2: Go8 / Top Research | H2: English | I2: 3 | J2: Only Tamil Nadu HSC, Maharashtra HSC and Karnataka PUC accepted as direct-entry Indian state boards | K2: 35 (2026 entry score, guide only). Prerequisites: grade 4 in an approved English subject and grade 4 in Mathematics Analysis & Approaches (SL or HL) or grade 4 in Mathematics Applications & Interpretation HL (AI SL not accepted) | L2: ABB (2026 entry score, guide only). Prerequisites: Mathematics and an approved A/AS Level English subject; minimum three A Levels, grade C or better in prerequisite subjects | M2: 81.00 (2026 entry score, guide only) - average of best four final-year subjects; prerequisites English and Mathematics | N2: 81.00 (2026 entry score, guide only) - average of best four final-year subjects; prerequisites English and Mathematics | O2: Academic merit against published entry score; meeting minimum entry and English requirements does not guarantee selection. July-start Actuarial Studies majors need higher maths (Calculus 2 entry level) | P2: IELTS 6.5 overall with no band less than 6.0 (course page header, international view) | Q2: None | R2: Direct international applications close: mid-year intake 2026 (Semester 2/July) 31 May 2026; start-year intake 2027 (Semester 1/February-March) 30 November 2026; mid-year 2027 31 May 2027 | S2: AUD 52,360 - 59,052 indicative first year fee (2026); AUD 56,451 - 62,464 (2027). Fees are subject-based (discipline fee bands) | T2: Melbourne International Undergraduate Scholarship and Melbourne Chancellor's Scholarship (automatically considered on application); A.G. Whitlam International Undergraduate Merit Scholarship (Bangladesh, India, Sri Lanka, Vietnam); International Undergraduate Partner Scholarship; Bachelor of Commerce Global Scholarship; Commerce Achievement Scholarship | U2: Australian Student visa (subclass 500) after accepting offer and receiving CoE; OSHC compulsory; full-time enrolment in CRICOS-registered course required; Genuine Student requirement applies | V2: Direct online application via the University of Melbourne application portal for both intakes; VTAC for start-year intake if completing an Australian Year 12 (anywhere) or the IB in Australia/NZ; applicants from certain countries must apply through an authorised education agent | W2: CRICOS 002143B. Intakes: March (Semester 1) and July (Semester 2) for internationals. Seven majors incl. Accounting, Actuarial Studies, Finance. AUD 17,000 deposit payable on acceptance. | X2: Confirmed | Y2: Sheet CBSE 88%+ and ISC 80%+ vs published 81.00 for both; sheet IB band 34-38 vs published 2026 guide score 35; sheet deadline 'May 31' is only the mid-year close - Semester 1 direct applications close 30 November; sheet A-level ABB matches | Z2: https://study.unimelb.edu.au/find/courses/undergraduate/bachelor-of-commerce/fees/ | AA2: 2026 fees Indicative first year fee AUD$52,360 - $59,052 [...] CRICOS code: 002143B | AB2: 13 September 2026 | AC2: yes | AD2: Pave verification, web-checked | AE2: Academic transcripts/certificates, evidence of English language proficiency, passport identity page; applicants who studied in certain countries must apply via an authorised agent for document verification | AF2: Deadlines published for 2026 mid-year and both 2027 intakes as of 13 September 2026 (study.unimelb.edu.au/how-to-apply/undergraduate-study/international-applications/applications) | AG2: 2026 (2027 also published) | AH2: AUD 154 non-refundable per direct international application (exemptions apply, e.g. sponsored applicants) | AI2: 2026-11-30 | AJ2: 81.00 (2026 entry score, guide only) - average of best four final-year subjects; prerequisites English and Mathematics | ISC: 81.00 (2026 entry score, guide only) - average of best four final-year subjects; prerequisites English and Mathematics
A3: AU-002 | B3: University of Melbourne | C3: Australia | D3: Bachelor of Science | E3: Bachelor | F3: https://study.unimelb.edu.au/find/courses/undergraduate/bachelor-of-science/ | G3: Go8 / Top Research | H3: English | I3: 3 | J3: Only Tamil Nadu HSC, Maharashtra HSC and Karnataka PUC accepted as direct-entry Indian state boards | K3: 31 (2026 entry score, guide only). Prerequisites: grade 4 in English/English B, grade 4 in Mathematics (AI HL, AA SL or AA HL), and grade 4 in one of Biology, Chemistry or Physics (HL or SL) | L3: BBB (2026 entry score, guide only). Prerequisites: Mathematics, one of Biology/Chemistry/Physics, and an approved A/AS Level English subject (or Maths + Further Maths + English); min. three A Levels, grade C in prerequisites | M3: 75.00 (2026 entry score, guide only) - average of best four final-year subjects; prerequisites English, Mathematics and one of Biology/Chemistry/Physics | N3: 75.00 (2026 entry score, guide only) - same basis as CBSE | O3: Academic merit against published entry score; subject prerequisites must be met with stated minimum grades | P3: IELTS 6.5 overall with no band less than 6.0 (course page header, international view) | Q3: None | R3: Direct international applications close: mid-year intake 2026 (Semester 2/July) 31 May 2026; start-year intake 2027 (Semester 1/February-March) 30 November 2026; mid-year 2027 31 May 2027 | S3: AUD 52,944 - 62,208 indicative first year fee (2026); AUD 55,556 - 65,344 (2027) | T3: Melbourne International Undergraduate Scholarship and Melbourne Chancellor's Scholarship (automatically considered on application); A.G. Whitlam International Undergraduate Merit Scholarship (Bangladesh, India, Sri Lanka, Vietnam); International Undergraduate Partner Scholarship | U3: Australian Student visa (subclass 500) after accepting offer and receiving CoE; OSHC compulsory; full-time enrolment in CRICOS-registered course required; Genuine Student requirement applies | V3: Direct online application via the University of Melbourne application portal for both intakes; VTAC for start-year intake if completing an Australian Year 12 (anywhere) or the IB in Australia/NZ; applicants from certain countries must apply through an authorised education agent | W3: CRICOS 002153M. Intakes: March and July. 40+ majors incl. computing, mathematics, psychology; gateway to graduate engineering/medicine. | X3: Confirmed | Y3: Sheet IB 32-36 vs published 31; sheet CBSE 85%+ vs 75.00; sheet ISC 78%+ vs 75.00; sheet fee AUD 52,944 matches published lower bound | Z3: https://study.unimelb.edu.au/find/courses/undergraduate/bachelor-of-science/fees/ | AA3: 2026 fees Indicative first year fee AUD$52,944 - $62,208 [...] CRICOS code: 002153M | AB3: 13 September 2026 | AC3: yes | AD3: Pave verification, web-checked | AE3: Academic transcripts/certificates, evidence of English language proficiency, passport identity page; applicants who studied in certain countries must apply via an authorised agent for document verification | AF3: Deadlines published for 2026 mid-year and both 2027 intakes as of 13 September 2026 (study.unimelb.edu.au/how-to-apply/undergraduate-study/international-applications/applications) | AG3: 2026 (2027 also published) | AH3: AUD 154 non-refundable per direct international application (exemptions apply, e.g. sponsored applicants) | AI3: 2026-11-30 | AJ3: 75.00 (2026 entry score, guide only) - average of best four final-year subjects; prerequisites English, Mathematics and one of Biology/Chemistry/Physics | ISC: 75.00 (2026 entry score, guide only) - same basis as CBSE
A4: AU-003 | B4: University of Melbourne | C4: Australia | D4: Bachelor of Arts | E4: Bachelor | F4: https://study.unimelb.edu.au/find/courses/undergraduate/bachelor-of-arts/ | G4: Go8 / Top Research | H4: English | I4: 3 | J4: Only Tamil Nadu HSC, Maharashtra HSC and Karnataka PUC accepted as direct-entry Indian state boards | K4: 30 (2026 entry score, guide only). Prerequisite: grade 4 in English or English B (SL or HL) | L4: BBB (2026 entry score, guide only). Prerequisite: an approved A/AS Level English subject; Economics majors strongly encouraged to take Mathematics; min. three A Levels | M4: 65.00 (2026 entry score, guide only) - average of best four final-year subjects; prerequisite English | N4: 65.00 (2026 entry score, guide only) - same basis as CBSE | O4: Academic merit against published entry score | P4: IELTS 6.5 overall with no band less than 6.0 (course page header, international view) | Q4: None | R4: Direct international applications close: mid-year intake 2026 (Semester 2/July) 31 May 2026; start-year intake 2027 (Semester 1/February-March) 30 November 2026; mid-year 2027 31 May 2027 | S4: AUD 38,004 - 56,252 indicative first year fee (2026); AUD 44,356 - 57,764 (2027) | T4: Melbourne International Undergraduate Scholarship and Melbourne Chancellor's Scholarship (automatically considered on application); A.G. Whitlam International Undergraduate Merit Scholarship (Bangladesh, India, Sri Lanka, Vietnam); International Undergraduate Partner Scholarship | U4: Australian Student visa (subclass 500) after accepting offer and receiving CoE; OSHC compulsory; full-time enrolment in CRICOS-registered course required; Genuine Student requirement applies | V4: Direct online application via the University of Melbourne application portal for both intakes; VTAC for start-year intake if completing an Australian Year 12 (anywhere) or the IB in Australia/NZ; applicants from certain countries must apply through an authorised education agent | W4: CRICOS 002167E. Intakes: March and July. 40+ majors across humanities and social sciences. | X4: Confirmed | Y4: Sheet A-level BBC vs published BBB; sheet CBSE 83%+ vs 65.00; sheet ISC 75%+ vs 65.00; sheet IB lower bound 30 matches published 30 | Z4: https://study.unimelb.edu.au/find/courses/undergraduate/bachelor-of-arts/fees/ | AA4: 2026 fees Indicative first year fee AUD$38,004 - $56,252 [...] CRICOS code: 002167E | AB4: 13 September 2026 | AC4: yes | AD4: Pave verification, web-checked | AE4: Academic transcripts/certificates, evidence of English language proficiency, passport identity page; applicants who studied in certain countries must apply via an authorised agent for document verification | AF4: Deadlines published for 2026 mid-year and both 2027 intakes as of 13 September 2026 (study.unimelb.edu.au/how-to-apply/undergraduate-study/international-applications/applications) | AG4: 2026 (2027 also published) | AH4: AUD 154 non-refundable per direct international application (exemptions apply, e.g. sponsored applicants) | AI4: 2026-11-30 | AJ4: 65.00 (2026 entry score, guide only) - average of best four final-year subjects; prerequisite English | ISC: 65.00 (2026 entry score, guide only) - same basis as CBSE
A5: AU-004 | B5: University of Melbourne | C5: Australia | D5: Bachelor of Design | E5: Bachelor | F5: https://study.unimelb.edu.au/find/courses/undergraduate/bachelor-of-design/ | G5: Go8 / Top Research | H5: English | I5: 3 | J5: Mathematical knowledge equivalent to VCE Mathematical Methods (study score 25+) required for Construction, Civil/Mechanical/Digital-Infrastructure Systems and Computing majors; any VCE Mathematics for Property major | K5: 30 (2026 entry score, guide only). Prerequisite: grade 4 in English or English B (SL or HL) | L5: BBB (2026 entry score, guide only). Prerequisite: an approved A/AS Level English subject; min. three A Levels | M5: 70.00 (2026 entry score, guide only) - average of best four final-year subjects | N5: 70.00 (2026 entry score, guide only) - same basis as CBSE | O5: Academic merit against published entry score; major-specific maths knowledge requirements | P5: IELTS 6.5 overall with no band less than 6.0 (course page header, international view) | Q5: None - entry is score-based; no portfolio required for admission | R5: Direct international applications close: mid-year intake 2026 (Semester 2/July) 31 May 2026; start-year intake 2027 (Semester 1/February-March) 30 November 2026; mid-year 2027 31 May 2027 | S5: AUD 43,868 - 57,900 indicative first year fee (2026); AUD 45,928 - 63,924 (2027) | T5: Melbourne International Undergraduate Scholarship and Melbourne Chancellor's Scholarship (automatically considered on application); A.G. Whitlam International Undergraduate Merit Scholarship (Bangladesh, India, Sri Lanka, Vietnam); International Undergraduate Partner Scholarship | U5: Australian Student visa (subclass 500) after accepting offer and receiving CoE; OSHC compulsory; full-time enrolment in CRICOS-registered course required; Genuine Student requirement applies | V5: Direct online application via the University of Melbourne application portal for both intakes; VTAC for start-year intake if completing an Australian Year 12 (anywhere) or the IB in Australia/NZ; applicants from certain countries must apply through an authorised education agent | W5: CRICOS 090744C. Intakes: March and July. Majors incl. architecture, landscape architecture, urban planning, construction, engineering systems. | X5: Confirmed | Y5: Sheet fee 'AUD 50,000-56,000' vs published AUD 43,868-57,900 (2026); sheet A-level BBC vs BBB; sheet CBSE 80%+ vs 70.00; sheet ISC 73%+ vs 70.00 | Z5: https://study.unimelb.edu.au/find/courses/undergraduate/bachelor-of-design/fees/ | AA5: 2026 fees Indicative first year fee AUD$43,868 - $57,900 [...] CRICOS code: 090744C | AB5: 13 September 2026 | AC5: yes | AD5: Pave verification, web-checked | AE5: Academic transcripts/certificates, evidence of English language proficiency, passport identity page; applicants who studied in certain countries must apply via an authorised agent for document verification | AF5: Deadlines published for 2026 mid-year and both 2027 intakes as of 13 September 2026 (study.unimelb.edu.au/how-to-apply/undergraduate-study/international-applications/applications) | AG5: 2026 (2027 also published) | AH5: AUD 154 non-refundable per direct international application (exemptions apply, e.g. sponsored applicants) | AI5: 2026-11-30 | AJ5: 70.00 (2026 entry score, guide only) - average of best four final-year subjects | ISC: 70.00 (2026 entry score, guide only) - same basis as CBSE
A6: AU-005 | B6: University of Melbourne | C6: Australia | D6: Bachelor of Biomedicine | E6: Bachelor | F6: https://study.unimelb.edu.au/find/courses/undergraduate/bachelor-of-biomedicine/ | G6: Go8 / Top Research | H6: English | I6: 3 | J6: Only Tamil Nadu HSC, Maharashtra HSC and Karnataka PUC accepted as direct-entry Indian state boards | K6: 35 (2026 entry score, guide only). Prerequisites: grade 4 in English/English B, grade 4 in Chemistry, grade 4 in Mathematics (AI HL, AA SL or AA HL) | L6: AAB (2026 entry score, guide only). Prerequisites: Chemistry, Mathematics and an approved A/AS Level English subject; min. three A Levels, grade C in prerequisites | M6: 91.00 (2026 entry score, guide only) - average of best four final-year subjects; prerequisites English, Chemistry and Mathematics | N6: 91.00 (2026 entry score, guide only) - same basis as CBSE | O6: Academic merit against published entry score; subject prerequisites (Chemistry + Mathematics + English) strictly applied | P6: IELTS 6.5 overall with no band less than 6.0 (course page header, international view) | Q6: None for the bachelor (graduate Doctor of Medicine entry later requires separate selection) | R6: Direct international applications close: mid-year intake 2026 (Semester 2/July) 31 May 2026; start-year intake 2027 (Semester 1/February-March) 30 November 2026; mid-year 2027 31 May 2027 | S6: AUD 54,780 - 61,460 indicative first year fee (2026); AUD 58,084 - 65,288 (2027) | T6: Melbourne International Undergraduate Scholarship and Melbourne Chancellor's Scholarship (automatically considered on application); A.G. Whitlam International Undergraduate Merit Scholarship (Bangladesh, India, Sri Lanka, Vietnam); International Undergraduate Partner Scholarship | U6: Australian Student visa (subclass 500) after accepting offer and receiving CoE; OSHC compulsory; full-time enrolment in CRICOS-registered course required; Genuine Student requirement applies | V6: Direct online application via the University of Melbourne application portal for both intakes; VTAC for start-year intake if completing an Australian Year 12 (anywhere) or the IB in Australia/NZ; applicants from certain countries must apply through an authorised education agent | W6: CRICOS 058838G. Intakes: March and July. Pathway toward graduate Doctor of Medicine (separate selection). | X6: Confirmed | Y6: Sheet IB 39-43 vs published 2026 guide score 35; sheet A-level AAA vs AAB; sheet CBSE 95%+ vs 91.00; sheet ISC 90%+ vs 91.00; sheet fee 52,000-60,000 vs published 54,780-61,460 | Z6: https://study.unimelb.edu.au/find/courses/undergraduate/bachelor-of-biomedicine/fees/ | AA6: 2026 fees Indicative first year fee AUD$54,780 - $61,460 [...] CRICOS code: 058838G | AB6: 13 September 2026 | AC6: yes | AD6: Pave verification, web-checked | AE6: Academic transcripts/certificates, evidence of English language proficiency, passport identity page; applicants who studied in certain countries must apply via an authorised agent for document verification | AF6: Deadlines published for 2026 mid-year and both 2027 intakes as of 13 September 2026 (study.unimelb.edu.au/how-to-apply/undergraduate-study/international-applications/applications) | AG6: 2026 (2027 also published) | AH6: AUD 154 non-refundable per direct international application (exemptions apply, e.g. sponsored applicants) | AI6: 2026-11-30 | AJ6: 91.00 (2026 entry score, guide only) - average of best four final-year subjects; prerequisites English, Chemistry and Mathematics | ISC: 91.00 (2026 entry score, guide only) - same basis as CBSE
A7: AU-006 | B7: University of Melbourne | C7: Australia | D7: Bachelor of Music | E7: Bachelor | F7: https://study.unimelb.edu.au/find/courses/undergraduate/bachelor-of-music-performance/ | G7: Go8 / Top Research | H7: English | I7: 3 | K7: No entry score published - 'Range of criteria used for selection' (audition-based). Prerequisite: grade 4 in English or English B (SL or HL) | L7: No entry score published - selection is audition/talent-based; approved A/AS Level English subject required | M7: No cutoff published - selection is audition-based; English prerequisite; best-four average basis applies for the academic component | N7: No cutoff published - selection is audition-based; English prerequisite | O7: Talent-based selection via audition; academic prerequisites (English) must also be met | P7: IELTS 6.5 overall with no band less than 6.0 (course page header, international view) | Q7: Audition required ('Selection into the Bachelor of Music (Performance) is talent-based. Applicants are required to complete an audition.') | R7: Direct international applications close: mid-year intake 2026 (Semester 2/July) 31 May 2026; start-year intake 2027 (Semester 1/February-March) 30 November 2026; mid-year 2027 31 May 2027; audition/supplementary-task courses close earlier via VTAC (before September) | S7: AUD 39,936 - 44,213 indicative first year fee (2026) for Bachelor of Music (Performance) | T7: Melbourne International Undergraduate Scholarship and Melbourne Chancellor's Scholarship (automatically considered on application); A.G. Whitlam International Undergraduate Merit Scholarship (Bangladesh, India, Sri Lanka, Vietnam); International Undergraduate Partner Scholarship | U7: Australian Student visa (subclass 500) after accepting offer and receiving CoE; OSHC compulsory; full-time enrolment in CRICOS-registered course required; Genuine Student requirement applies | V7: Direct online application via the University of Melbourne application portal for both intakes; VTAC for start-year intake if completing an Australian Year 12 (anywhere) or the IB in Australia/NZ; applicants from certain countries must apply through an authorised education agent. VTAC applications for degrees requiring auditions (incl. Music) close before September each year | W7: CRICOS 058837J (Performance stream). February (Semester 1) intake only; Southbank campus. The generic 'Bachelor of Music' URL in the source sheet is dead: Melbourne now lists separate stream degrees - Performance, Composition, Interactive Composition, Music Studies, Musicology & Ethnomusicology; data here is for the Performance stream. | X7: Confirmed | Y7: Source course_url (bachelor-of-music) is dead - course restructured into stream-specific degrees; sheet IB 29 / CBSE 80%+ / ISC 73%+ / A-level 'BB+' have no published basis (no entry scores published - audition-based); sheet fee 42,000-48,000 vs published 39,936-44,213 (Performance); sheet intake 'May 31 deadline' not applicable as stated | Z7: https://study.unimelb.edu.au/find/courses/undergraduate/bachelor-of-music-performance/fees/ | AA7: Selection into the Bachelor of Music (Performance) is talent-based. Applicants are required to complete an audition. | AB7: 13 September 2026 | AC7: yes | AD7: Pave verification, web-checked | AE7: Academic transcripts/certificates, evidence of English language proficiency, passport identity page; applicants who studied in certain countries must apply via an authorised agent for document verification; audition (performance stream) | AF7: Course-specific audition deadlines not centrally published on the pages checked 13 September 2026 - confirm with the Melbourne Conservatorium | AG7: 2026 | AH7: AUD 154 non-refundable per direct international application (exemptions apply, e.g. sponsored applicants) | AJ7: No cutoff published - selection is audition-based; English prerequisite; best-four average basis applies for the academic component | ISC: No cutoff published - selection is audition-based; English prerequisite
A8: AU-007 | B8: University of Sydney | C8: Australia | D8: Bachelor of Commerce | E8: Bachelor | F8: https://www.sydney.edu.au/courses/courses/uc/bachelor-of-commerce.html | G8: Go8 / Top Research | H8: English | I8: 3 | J8: Indian State Board Higher Secondary School Certificate: 95 (2026); ATAR equivalent 96.0 | K8: 38 (2026 indicative entry score, international; 'All scores listed are a guide for admission and subject to change') | L8: 17 points from best 3 A2 subjects / 19 from best 4. A-level aggregate from A2 subjects, A*=6 A=5 B=4 C=3 D=2 E=1; first figure = 3 subjects, second = 4 subjects (AS not counted) | M8: 19.0 aggregate (2026 indicative entry score). CBSE aggregate basis: English or Hindi plus best four remaining externally examined subjects, graded A1=4, A2=3.5, B1=3, B2=2.5, C1=2, C2=1.5, D1=1, D2=0.5 (max 20; five A1s with 96+ exam average deemed 21) | N8: 94 (2026 indicative entry score). ISC basis: average of the best four subjects including English | O8: Rank-based admission on qualification entry score; scholarship rounds have separate deadlines | P8: IELTS: 'A minimum result of 7.0 overall and a minimum result of 6.0 in each band' (course-specific); TOEFL iBT 96 overall (R/L/S 17, W 19) | Q8: None. No prerequisites; assumed knowledge: Mathematics Standard or higher depending on majors | R8: International direct applications close 1 December of the year prior to commencement for Semester 1 (February) and 29 May of the commencing year for Semester 2 (August) | S8: A$56,300 international tuition fee for 2026 (first-year estimate, 48 credit points) | T8: Vice-Chancellor's International Scholarships Scheme (merit-based, assessed from the admission application); Sydney International Student Award | U8: Australian Student visa (subclass 500) after acceptance and CoE; OSHC required; available to student visa holders (course pages state 'Available to student visa holders') | V8: Three ways: apply directly to the University (online), via an authorised agent, or via UAC - UAC is mandatory if completing an Australian Year 12 (anywhere) or the IB in Australia | W8: CRICOS 012849G. Intakes: Semester 1 (February) and Semester 2 (August). 144 credit points. Business School triple accredited. | X8: Confirmed | Y8: Sheet IELTS 6.5/6.0 vs published 7.0 overall/6.0 bands; sheet fee 50,000 vs published 56,300; sheet CBSE '88%+' uses wrong metric (Sydney publishes a 20-point grade aggregate: 19.0); sheet ISC 80%+ vs 94; sheet deadline 'May 15' vs published 1 Dec (S1)/29 May (S2); sheet IB band 34-38: published figure is 38 | Z8: https://www.sydney.edu.au/courses/courses/uc/bachelor-of-commerce.html | AA8: IELTS score: A minimum result of 7.0 overall and a minimum result of 6.0 in each band; International Full Fee Paying Rate $56,300 (2026) | AB8: 13 September 2026 | AC8: yes | AD8: Pave verification, web-checked | AE8: Academic transcripts and completion certificates, English test evidence, passport; supplementary evidence via UAC where applicable | AF8: Standing university-wide closing dates published (sydney.edu.au/study/applying/application-dates.html), checked 13 September 2026; for 2027 Semester 1 that means 1 December 2026 | AG8: 2026 | AH8: A$150.00 non-refundable application processing fee (covers all applications made within one year); exemptions incl. full scholarship/sponsorship holders | AI8: 2026-12-01 | AJ8: 19.0 aggregate (2026 indicative entry score). CBSE aggregate basis: English or Hindi plus best four remaining externally examined subjects, graded A1=4, A2=3.5, B1=3, B2=2.5, C1=2, C2=1.5, D1=1, D2=0.5 (max 20; five A1s with 96+ exam average deemed 21) | ISC: 94 (2026 indicative entry score). ISC basis: average of the best four subjects including English
A9: AU-008 | B9: University of Sydney | C9: Australia | D9: Bachelor of Science | E9: Bachelor | F9: https://www.sydney.edu.au/courses/courses/uc/bachelor-of-science.html | G9: Go8 / Top Research | H9: English | I9: 3 | J9: ATAR equivalent 80.0 | K9: 29 (2026 indicative entry score, international) | L9: 13 points from best 3 A2 subjects / 13 from best 4. A-level aggregate from A2 subjects, A*=6 A=5 B=4 C=3 D=2 E=1; first figure = 3 subjects, second = 4 subjects (AS not counted) | M9: 14.0 aggregate (2026 indicative entry score). CBSE aggregate basis: English or Hindi plus best four remaining externally examined subjects, graded A1=4, A2=3.5, B1=3, B2=2.5, C1=2, C2=1.5, D1=1, D2=0.5 (max 20; five A1s with 96+ exam average deemed 21) | N9: 84 (2026 indicative entry score). ISC basis: average of the best four subjects including English | O9: Rank-based admission on qualification entry score | P9: IELTS: 'A minimum result of 6.5 overall and a minimum result of 6.0 in each band' | Q9: None. No prerequisites; assumed knowledge: Mathematics Advanced | R9: International direct applications close 1 December of the year prior to commencement for Semester 1 (February) and 29 May of the commencing year for Semester 2 (August) | S9: A$60,600 international tuition fee for 2026 (first-year estimate) | T9: Vice-Chancellor's International Scholarships Scheme (merit-based, assessed from the admission application); Sydney International Student Award | U9: Australian Student visa (subclass 500) after acceptance and CoE; OSHC required; available to student visa holders (course pages state 'Available to student visa holders') | V9: Three ways: apply directly to the University (online), via an authorised agent, or via UAC - UAC is mandatory if completing an Australian Year 12 (anywhere) or the IB in Australia | W9: CRICOS 000719E. Intakes: Semester 1 (February) and Semester 2 (August). 144 credit points. | X9: Confirmed | Y9: Sheet IB 32-36 vs published 29; sheet fee 49,000 vs 60,600; sheet CBSE '85%+' wrong metric (published 14.0/20 aggregate); sheet ISC 78%+ vs 84; sheet ATAR ~85 vs published 80.0; sheet deadline 15 May wrong | Z9: https://www.sydney.edu.au/courses/courses/uc/bachelor-of-science.html | AA9: IELTS score: A minimum result of 6.5 overall and a minimum result of 6.0 in each band; International Full Fee Paying Rate $60,600 (2026) | AB9: 13 September 2026 | AC9: yes | AD9: Pave verification, web-checked | AE9: Academic transcripts and completion certificates, English test evidence, passport; supplementary evidence via UAC where applicable | AF9: Standing university-wide closing dates published (sydney.edu.au/study/applying/application-dates.html), checked 13 September 2026; for 2027 Semester 1 that means 1 December 2026 | AG9: 2026 | AH9: A$150.00 non-refundable application processing fee (covers all applications made within one year); exemptions incl. full scholarship/sponsorship holders | AI9: 2026-12-01 | AJ9: 14.0 aggregate (2026 indicative entry score). CBSE aggregate basis: English or Hindi plus best four remaining externally examined subjects, graded A1=4, A2=3.5, B1=3, B2=2.5, C1=2, C2=1.5, D1=1, D2=0.5 (max 20; five A1s with 96+ exam average deemed 21) | ISC: 84 (2026 indicative entry score). ISC basis: average of the best four subjects including English
A10: AU-009 | B10: University of Sydney | C10: Australia | D10: Bachelor of Arts | E10: Bachelor | F10: https://www.sydney.edu.au/courses/courses/uc/bachelor-of-arts.html | G10: Go8 / Top Research | H10: English | I10: 3 | J10: ATAR equivalent 75.0 | K10: 26 (2026 indicative entry score, international) | L10: 12 points from best 3 A2 subjects / 12 from best 4. A-level aggregate from A2 subjects, A*=6 A=5 B=4 C=3 D=2 E=1; first figure = 3 subjects, second = 4 subjects (AS not counted) | M10: 12.5 aggregate (2026 indicative entry score). CBSE aggregate basis: English or Hindi plus best four remaining externally examined subjects, graded A1=4, A2=3.5, B1=3, B2=2.5, C1=2, C2=1.5, D1=1, D2=0.5 (max 20; five A1s with 96+ exam average deemed 21) | N10: 81 (2026 indicative entry score). ISC basis: average of the best four subjects including English | O10: Rank-based admission on qualification entry score | P10: IELTS: 'A minimum result of 6.5 overall and a minimum result of 6.0 in each band' | Q10: None. No prerequisites; assumed knowledge depends on majors chosen | R10: International direct applications close 1 December of the year prior to commencement for Semester 1 (February) and 29 May of the commencing year for Semester 2 (August) | S10: A$52,500 international tuition fee for 2026 (first-year estimate) | T10: Vice-Chancellor's International Scholarships Scheme (merit-based, assessed from the admission application); Sydney International Student Award | U10: Australian Student visa (subclass 500) after acceptance and CoE; OSHC required; available to student visa holders (course pages state 'Available to student visa holders') | V10: Three ways: apply directly to the University (online), via an authorised agent, or via UAC - UAC is mandatory if completing an Australian Year 12 (anywhere) or the IB in Australia | W10: CRICOS 000705M. Intakes: Semester 1 (February) and Semester 2 (August). 144 credit points, 40+ majors. | X10: Confirmed | Y10: Sheet IB 29-33 vs published 26; sheet fee 45,000 vs 52,500; sheet CBSE '82%+' wrong metric (published 12.5/20 aggregate); sheet ISC 75%+ vs 81; sheet deadline 15 May wrong | Z10: https://www.sydney.edu.au/courses/courses/uc/bachelor-of-arts.html | AA10: IELTS score: A minimum result of 6.5 overall and a minimum result of 6.0 in each band; International Full Fee Paying Rate $52,500 (2026) | AB10: 13 September 2026 | AC10: yes | AD10: Pave verification, web-checked | AE10: Academic transcripts and completion certificates, English test evidence, passport; supplementary evidence via UAC where applicable | AF10: Standing university-wide closing dates published (sydney.edu.au/study/applying/application-dates.html), checked 13 September 2026; for 2027 Semester 1 that means 1 December 2026 | AG10: 2026 | AH10: A$150.00 non-refundable application processing fee (covers all applications made within one year); exemptions incl. full scholarship/sponsorship holders | AI10: 2026-12-01 | AJ10: 12.5 aggregate (2026 indicative entry score). CBSE aggregate basis: English or Hindi plus best four remaining externally examined subjects, graded A1=4, A2=3.5, B1=3, B2=2.5, C1=2, C2=1.5, D1=1, D2=0.5 (max 20; five A1s with 96+ exam average deemed 21) | ISC: 81 (2026 indicative entry score). ISC basis: average of the best four subjects including English
A11: AU-010 | B11: University of Sydney | C11: Australia | D11: Bachelor of Engineering (Honours) | E11: Bachelor | F11: https://www.sydney.edu.au/courses/courses/uc/bachelor-of-engineering-honours-flexible-first-year.html | G11: Go8 / Top Research | H11: English | I11: 4 | J11: ATAR equivalent 85.0. Mathematics prerequisite applies; assumed knowledge Mathematics Extension 1, Chemistry, Physics | K11: 31 (2026 indicative entry score, international; Flexible First Year stream) | L11: 14 points from best 3 A2 subjects / 14 from best 4. A-level aggregate from A2 subjects, A*=6 A=5 B=4 C=3 D=2 E=1; first figure = 3 subjects, second = 4 subjects (AS not counted) | M11: 15.5 aggregate (2026 indicative entry score). CBSE aggregate basis: English or Hindi plus best four remaining externally examined subjects, graded A1=4, A2=3.5, B1=3, B2=2.5, C1=2, C2=1.5, D1=1, D2=0.5 (max 20; five A1s with 96+ exam average deemed 21) | N11: 87 (2026 indicative entry score). ISC basis: average of the best four subjects including English | O11: Rank-based; maths prerequisite enforced | P11: IELTS: 'A minimum result of 6.5 overall and a minimum result of 6.0 in each band' | Q11: None; Mathematics prerequisite must be satisfied | R11: Semester 1 (February) intake only for this course; international direct applications close 1 December of the prior year | S11: A$60,600 international tuition fee for 2026 (first-year estimate) | T11: Vice-Chancellor's International Scholarships Scheme (merit-based, assessed from the admission application); Sydney International Student Award | U11: Australian Student visa (subclass 500) after acceptance and CoE; OSHC required; available to student visa holders (course pages state 'Available to student visa holders') | V11: Three ways: apply directly to the University (online), via an authorised agent, or via UAC - UAC is mandatory if completing an Australian Year 12 (anywhere) or the IB in Australia | W11: CRICOS 083109M (Flexible First Year). 192 credit points, Semester 1 intake only. The source sheet's generic BE(Hons) URL is dead - Sydney lists per-stream pages (Civil, Electrical, Mechanical, Software etc.); Flexible First Year page used as the generic entry route. | X11: Confirmed | Y11: Source course_url dead (404) - course split into stream pages; sheet IB 37-40 vs published 31 (FFY); sheet CBSE '90%+' wrong metric (published 15.5/20); sheet ISC 85%+ vs 87; sheet fee 50,000 vs 60,600; sheet ATAR ~95 vs 85.0; sheet deadline 15 May wrong; Semester 2 entry not offered | Z11: https://www.sydney.edu.au/courses/courses/uc/bachelor-of-engineering-honours-flexible-first-year.html | AA11: This course has a Mathematics prerequisite. [...] Assumed knowledge: Mathematics Extension 1, Chemistry, Physics; International Full Fee Paying Rate $60,600 (2026) | AB11: 13 September 2026 | AC11: yes | AD11: Pave verification, web-checked | AE11: Academic transcripts and completion certificates, English test evidence, passport; supplementary evidence via UAC where applicable | AF11: Standing university-wide closing dates published (sydney.edu.au/study/applying/application-dates.html), checked 13 September 2026; for 2027 Semester 1 that means 1 December 2026 | AG11: 2026 | AH11: A$150.00 non-refundable application processing fee (covers all applications made within one year); exemptions incl. full scholarship/sponsorship holders | AI11: 2026-12-01 | AJ11: 15.5 aggregate (2026 indicative entry score). CBSE aggregate basis: English or Hindi plus best four remaining externally examined subjects, graded A1=4, A2=3.5, B1=3, B2=2.5, C1=2, C2=1.5, D1=1, D2=0.5 (max 20; five A1s with 96+ exam average deemed 21) | ISC: 87 (2026 indicative entry score). ISC basis: average of the best four subjects including English
A12: AU-011 | B12: University of Sydney | C12: Australia | D12: Bachelor of Laws (LLB) | E12: Bachelor | F12: https://www.sydney.edu.au/courses/courses/uc/bachelor-of-arts-and-bachelor-of-laws.html | G12: Go8 / Top Research | H12: English | I12: 5 | J12: ATAR equivalent 95.5. Assumed knowledge: English Advanced | K12: 38 (2026 indicative entry score, international, BA/LLB combined) | L12: 16 points from best 3 A2 subjects / 18 from best 4. A-level aggregate from A2 subjects, A*=6 A=5 B=4 C=3 D=2 E=1; first figure = 3 subjects, second = 4 subjects (AS not counted) | M12: 18.5 aggregate (2026 indicative entry score). CBSE aggregate basis: English or Hindi plus best four remaining externally examined subjects, graded A1=4, A2=3.5, B1=3, B2=2.5, C1=2, C2=1.5, D1=1, D2=0.5 (max 20; five A1s with 96+ exam average deemed 21) | N12: 94 (2026 indicative entry score). ISC basis: average of the best four subjects including English | O12: Rank-based on combined-degree entry score; no LLB-specific test | P12: IELTS: 'A minimum result of 7.5 overall and a minimum result of 7.0 in each band' (Law combined degrees) | Q12: None (Sydney does not use an admission test for undergraduate law) | R12: International direct applications close 1 December of the year prior to commencement for Semester 1 (February) and 29 May of the commencing year for Semester 2 (August) | S12: A$56,300 international tuition fee for 2026 (first-year estimate, BA/LLB) | T12: Vice-Chancellor's International Scholarships Scheme (merit-based, assessed from the admission application); Sydney International Student Award | U12: Australian Student visa (subclass 500) after acceptance and CoE; OSHC required; available to student visa holders (course pages state 'Available to student visa holders') | V12: Three ways: apply directly to the University (online), via an authorised agent, or via UAC - UAC is mandatory if completing an Australian Year 12 (anywhere) or the IB in Australia | W12: CRICOS 006441D (BA/LLB). Intakes: Semester 1 (February) and Semester 2 (August). Sydney does NOT offer a standalone 4-year undergraduate LLB - undergraduate law is a 5-year combined degree (Arts/Commerce/Science/etc. + LLB); BA/LLB used as reference combination. | X12: Confirmed | Y12: Sheet describes a 4-year direct-entry LLB that does not exist (dead URL; undergraduate law is 5-year combined only); sheet IB 41-45 vs published 38; sheet IELTS 7.0/6.5 vs published 7.5 overall/7.0 bands; sheet fee 52,000 vs 56,300; sheet CBSE 95%+ wrong metric (18.5/20); sheet ISC 92%+ vs 94 | Z12: https://www.sydney.edu.au/courses/courses/uc/bachelor-of-arts-and-bachelor-of-laws.html | AA12: IELTS score: A minimum result of 7.5 overall and a minimum result of 7.0 in each band; DURATION 5 years full-time | AB12: 13 September 2026 | AC12: yes | AD12: Pave verification, web-checked | AE12: Academic transcripts and completion certificates, English test evidence, passport; supplementary evidence via UAC where applicable | AF12: Standing university-wide closing dates published (sydney.edu.au/study/applying/application-dates.html), checked 13 September 2026; for 2027 Semester 1 that means 1 December 2026 | AG12: 2026 | AH12: A$150.00 non-refundable application processing fee (covers all applications made within one year); exemptions incl. full scholarship/sponsorship holders | AI12: 2026-12-01 | AJ12: 18.5 aggregate (2026 indicative entry score). CBSE aggregate basis: English or Hindi plus best four remaining externally examined subjects, graded A1=4, A2=3.5, B1=3, B2=2.5, C1=2, C2=1.5, D1=1, D2=0.5 (max 20; five A1s with 96+ exam average deemed 21) | ISC: 94 (2026 indicative entry score). ISC basis: average of the best four subjects including English
A13: AU-012 | B13: University of Sydney | C13: Australia | D13: Bachelor of Psychology (Honours) | E13: Bachelor | F13: https://www.sydney.edu.au/courses/courses/uc/bachelor-of-psychology-honours.html | G13: Go8 / Top Research | H13: English | I13: 4 | J13: ATAR equivalent 91.0. Assumed knowledge: Mathematics Advanced | K13: 34 (2026 indicative entry score, international) | L13: 15 points from best 3 A2 subjects / 16 from best 4. A-level aggregate from A2 subjects, A*=6 A=5 B=4 C=3 D=2 E=1; first figure = 3 subjects, second = 4 subjects (AS not counted) | M13: 17.5 aggregate (2026 indicative entry score). CBSE aggregate basis: English or Hindi plus best four remaining externally examined subjects, graded A1=4, A2=3.5, B1=3, B2=2.5, C1=2, C2=1.5, D1=1, D2=0.5 (max 20; five A1s with 96+ exam average deemed 21) | N13: 91 (2026 indicative entry score). ISC basis: average of the best four subjects including English | O13: Rank-based admission on qualification entry score | P13: IELTS: 'A minimum result of 6.5 overall and a minimum result of 6.0 in each band' | Q13: None | R13: Semester 1 (February) intake only for this course; international direct applications close 1 December of the prior year | S13: A$60,600 international tuition fee for 2026 (first-year estimate) | T13: Vice-Chancellor's International Scholarships Scheme (merit-based, assessed from the admission application); Sydney International Student Award | U13: Australian Student visa (subclass 500) after acceptance and CoE; OSHC required; available to student visa holders (course pages state 'Available to student visa holders') | V13: Three ways: apply directly to the University (online), via an authorised agent, or via UAC - UAC is mandatory if completing an Australian Year 12 (anywhere) or the IB in Australia | W13: CRICOS 107970E. 192 credit points; APAC-accredited pathway to psychologist registration. Note a separate 3-year Bachelor of Psychology (CRICOS 107969J) also exists. | X13: Confirmed | Y13: Sheet fee 49,000 vs published 60,600; sheet CBSE '88%+' wrong metric (published 17.5/20); sheet ISC 80%+ vs 91; sheet deadline 15 May wrong; Semester 2 entry not offered; sheet IB lower bound 34 matches published 34 | Z13: https://www.sydney.edu.au/courses/courses/uc/bachelor-of-psychology-honours.html | AA13: IELTS score: A minimum result of 6.5 overall and a minimum result of 6.0 in each band; International Full Fee Paying Rate $60,600 (2026) | AB13: 13 September 2026 | AC13: yes | AD13: Pave verification, web-checked | AE13: Academic transcripts and completion certificates, English test evidence, passport; supplementary evidence via UAC where applicable | AF13: Standing university-wide closing dates published (sydney.edu.au/study/applying/application-dates.html), checked 13 September 2026; for 2027 Semester 1 that means 1 December 2026 | AG13: 2026 | AH13: A$150.00 non-refundable application processing fee (covers all applications made within one year); exemptions incl. full scholarship/sponsorship holders | AI13: 2026-12-01 | AJ13: 17.5 aggregate (2026 indicative entry score). CBSE aggregate basis: English or Hindi plus best four remaining externally examined subjects, graded A1=4, A2=3.5, B1=3, B2=2.5, C1=2, C2=1.5, D1=1, D2=0.5 (max 20; five A1s with 96+ exam average deemed 21) | ISC: 91 (2026 indicative entry score). ISC basis: average of the best four subjects including English
A14: AU-013 | B14: UNSW Sydney | C14: Australia | D14: Bachelor of Commerce | E14: Bachelor | F14: https://www.unsw.edu.au/study/undergraduate/bachelor-of-commerce | G14: Go8 / Top Research | H14: English | I14: 3 | J14: India State Board 98.0 (Maharashtra, Karnataka, Tamil Nadu only); SAT 1300 (with completed senior secondary) | K14: 36.0 international direct entry requirement (2026); for context the domestic 2026 lowest selection rank was 97.0 (IB guide 41.0) | L14: 15.0 points international direct entry (2026). A-level basis: minimum two A2 subjects; score aggregated from best 2-4 A2 subjects, A*=6 A=5 B=4 C=3 D=2 E=1 | M14: 85.0 (2026 international direct entry). CBSE basis: average percentage across English or Hindi plus best four remaining subjects (range marks use mid-point) | N14: 92.0 (2026 international direct entry, Indian School Certificate CISCE) | O14: Rank/score-based; International Admissions Diversity Pathway can add 5 points to International ATAR for eligible applicants | P14: IELTS 7.0 overall (min 6.0 in each subtest) - UNSW Business School requirement (standard UNSW UG is 6.5/6.0) | Q14: None. Assumed knowledge: Mathematics Advanced | R14: Rolling offer rounds. Published Term 1 2027 undergraduate international round deadlines: 14 May 2026, 16 July 2026, 20 August 2026, 24 September 2026 (completed-application deadlines per round); later rounds published progressively | S14: A$56,500 indicative first year fee 2026 (indicative full fee to complete degree $180,500) | T14: International Scientia Coursework Scholarship (full tuition or $20,000/year); UNSW International Student Award (20% tuition contribution, 500-word personal statement) | U14: Australian Student visa (subclass 500) after acceptance and CoE; OSHC required | V14: Direct via the UNSW Applicant Portal, via an authorised agent, or via UAC (UAC required if completing an Australian Year 12; IB students in Australia may use UAC or apply direct) | W14: CRICOS 001919M. Program 3502, UAC 424000. Commencing Terms 1, 2 & 3 (Feb/May/Sep). 16 majors. | X14: Confirmed | Y14: Sheet IELTS 6.5/6.0 vs published Business School 7.0 overall/6.0; sheet CBSE 90%+ vs published 85.0; sheet ISC 85%+ vs 92.0; sheet fee 56,500 matches; sheet deadline '14 May' is only round 1 of the 2027 offer rounds | Z14: https://www.unsw.edu.au/study/undergraduate/bachelor-of-commerce | AA14: All India Senior School Certificate (CBSE) 85.0; Indian School Certificate (CISCE) 92.0; International Baccalaureate Diploma (IB) 36.0; 2026 Indicative First Year Fee $56,500* | AB14: 13 September 2026 | AC14: yes | AD14: Pave verification, web-checked | AE14: Academic transcripts/certificates, English evidence, passport; personal statement for some scholarships; submit via UNSW Applicant Portal | AF14: UNSW publishes per-round offer schedules rather than a single closing date (unsw.edu.au/study/international-students/admissions-info, checked 13 September 2026); final T1 2027 round not yet listed, so deadline_iso_close left blank | AG14: 2026 | AH14: A non-refundable application fee of $150 AUD may be payable via the UNSW Applicant Portal (credit card; some exclusions) | AJ14: 85.0 (2026 international direct entry). CBSE basis: average percentage across English or Hindi plus best four remaining subjects (range marks use mid-point) | ISC: 92.0 (2026 international direct entry, Indian School Certificate CISCE)
A15: AU-014 | B15: UNSW Sydney | C15: Australia | D15: Bachelor of Engineering (Honours) | E15: Bachelor | F15: https://www.unsw.edu.au/study/undergraduate/bachelor-of-engineering-honours | G15: Go8 / Top Research | H15: English | I15: 4 | J15: India State Board 96.0 (MH/KA/TN only); SAT 1260 | K15: 35.0 international direct entry requirement (2026) | L15: 13.0 points international direct entry (2026). A-level basis: minimum two A2 subjects; score aggregated from best 2-4 A2 subjects, A*=6 A=5 B=4 C=3 D=2 E=1 | M15: 81.0 (2026 international direct entry). CBSE basis: average percentage across English or Hindi plus best four remaining subjects (range marks use mid-point) | N15: 90.0 (2026 international direct entry) | O15: Rank/score-based; flexible-entry then specialisation into streams (Civil, Mechanical, Electrical, Software, Chemical, Mining etc.) | P15: IELTS 6.5 overall (min 6.0 in each subtest) - standard UNSW requirement | Q15: None. Assumed knowledge: Mathematics Extension 1, Physics | R15: Rolling offer rounds. Published Term 1 2027 undergraduate international round deadlines: 14 May 2026, 16 July 2026, 20 August 2026, 24 September 2026 (completed-application deadlines per round); later rounds published progressively | S15: A$61,500 indicative first year fee 2026 | T15: International Scientia Coursework Scholarship (full tuition or $20,000/year); UNSW International Student Award (20% tuition contribution, 500-word personal statement) | U15: Australian Student visa (subclass 500) after acceptance and CoE; OSHC required | V15: Direct via the UNSW Applicant Portal, via an authorised agent, or via UAC (UAC required if completing an Australian Year 12; IB students in Australia may use UAC or apply direct) | W15: CRICOS 056835E. UAC 425000. Commencing Terms 1, 2 & 3. | X15: Confirmed | Y15: Sheet IB 38-42 vs published international direct entry 35.0; sheet CBSE 92%+ vs 81.0; sheet ISC 88%+ vs 90.0; sheet fee 58,000 vs 61,500; sheet deadline 14 May is only an offer-round date | Z15: https://www.unsw.edu.au/study/undergraduate/bachelor-of-engineering-honours | AA15: All India Senior School Certificate (CBSE) 81.0; International Baccalaureate Diploma (IB) 35.0; 2026 Indicative First Year Fee $61,500* | AB15: 13 September 2026 | AC15: yes | AD15: Pave verification, web-checked | AE15: Academic transcripts/certificates, English evidence, passport; personal statement for some scholarships; submit via UNSW Applicant Portal | AF15: UNSW publishes per-round offer schedules rather than a single closing date (unsw.edu.au/study/international-students/admissions-info, checked 13 September 2026); final T1 2027 round not yet listed, so deadline_iso_close left blank | AG15: 2026 | AH15: A non-refundable application fee of $150 AUD may be payable via the UNSW Applicant Portal (credit card; some exclusions) | AJ15: 81.0 (2026 international direct entry). CBSE basis: average percentage across English or Hindi plus best four remaining subjects (range marks use mid-point) | ISC: 90.0 (2026 international direct entry)
A16: AU-015 | B16: UNSW Sydney | C16: Australia | D16: Bachelor of Computer Science | E16: Bachelor | F16: https://www.unsw.edu.au/study/undergraduate/bachelor-of-computer-science | G16: Go8 / Top Research | H16: English | I16: 3 | J16: India State Board 95.0 (MH/KA/TN only) | K16: 34.0 international direct entry requirement (2026); domestic 2026 LSR 93.0 (IB guide 37.0) | L16: 12.0 points international direct entry (2026). A-level basis: minimum two A2 subjects; score aggregated from best 2-4 A2 subjects, A*=6 A=5 B=4 C=3 D=2 E=1 | M16: 81.0 (2026 international direct entry). CBSE basis: average percentage across English or Hindi plus best four remaining subjects (range marks use mid-point) | N16: 89.0 (2026 international direct entry) | O16: Rank/score-based | P16: IELTS 6.5 overall (min 6.0 in each subtest) - standard UNSW requirement | Q16: None. Assumed knowledge: Mathematics Extension 1 | R16: Rolling offer rounds. Published Term 1 2027 undergraduate international round deadlines: 14 May 2026, 16 July 2026, 20 August 2026, 24 September 2026 (completed-application deadlines per round); later rounds published progressively | S16: A$61,000 indicative first year fee 2026 | T16: International Scientia Coursework Scholarship (full tuition or $20,000/year); UNSW International Student Award (20% tuition contribution, 500-word personal statement) | U16: Australian Student visa (subclass 500) after acceptance and CoE; OSHC required | V16: Direct via the UNSW Applicant Portal, via an authorised agent, or via UAC (UAC required if completing an Australian Year 12; IB students in Australia may use UAC or apply direct) | W16: CRICOS 015784F. Official degree title on the page is 'Bachelor of Science (Computer Science)', program 3778, UAC 425800. Commencing Terms 1, 2 & 3. (UNSW's separate flagship Bachelor of Computer Science program 3778 page carries this title.) | X16: Confirmed | Y16: Sheet IB 37-40 vs published international direct entry 34.0 (37 is the domestic LSR-derived guide); sheet CBSE 90%+ vs 81.0; sheet ISC 85%+ vs 89.0; sheet fee 56,000 vs 61,000; page titles the degree 'Bachelor of Science (Computer Science)' | Z16: https://www.unsw.edu.au/study/undergraduate/bachelor-of-computer-science | AA16: All India Senior School Certificate (CBSE) 81.0; International Baccalaureate Diploma (IB) 34.0; 2026 Indicative First Year Fee $61,000* | AB16: 13 September 2026 | AC16: yes | AD16: Pave verification, web-checked | AE16: Academic transcripts/certificates, English evidence, passport; personal statement for some scholarships; submit via UNSW Applicant Portal | AF16: UNSW publishes per-round offer schedules rather than a single closing date (unsw.edu.au/study/international-students/admissions-info, checked 13 September 2026); final T1 2027 round not yet listed, so deadline_iso_close left blank | AG16: 2026 | AH16: A non-refundable application fee of $150 AUD may be payable via the UNSW Applicant Portal (credit card; some exclusions) | AJ16: 81.0 (2026 international direct entry). CBSE basis: average percentage across English or Hindi plus best four remaining subjects (range marks use mid-point) | ISC: 89.0 (2026 international direct entry)
A17: AU-016 | B17: UNSW Sydney | C17: Australia | D17: Bachelor of Science (Advanced Mathematics) | E17: Bachelor | F17: https://www.unsw.edu.au/study/undergraduate/bachelor-of-science-advanced-mathematics-honours | G17: Go8 / Top Research | H17: English | I17: 4 | J17: India State Board 95.0 (MH/KA/TN only) | K17: 34.0 international direct entry requirement (2026); domestic 2026 LSR 93.0 (IB guide 37.0) | L17: 12.0 points international direct entry (2026). A-level basis: minimum two A2 subjects; score aggregated from best 2-4 A2 subjects, A*=6 A=5 B=4 C=3 D=2 E=1 | M17: 81.0 (2026 international direct entry). CBSE basis: average percentage across English or Hindi plus best four remaining subjects (range marks use mid-point) | N17: 89.0 (2026 international direct entry) | O17: Rank/score-based; embedded Honours (research) year | P17: IELTS 6.5 overall (min 6.0 in each subtest) - standard UNSW requirement | Q17: None. Assumed knowledge: Mathematics Extension 1 | R17: Rolling offer rounds. Published Term 1 2027 undergraduate international round deadlines: 14 May 2026, 16 July 2026, 20 August 2026, 24 September 2026 (completed-application deadlines per round); later rounds published progressively | S17: A$61,000 indicative first year fee 2026 | T17: International Scientia Coursework Scholarship (full tuition or $20,000/year); UNSW International Student Award (20% tuition contribution, 500-word personal statement) | U17: Australian Student visa (subclass 500) after acceptance and CoE; OSHC required | V17: Direct via the UNSW Applicant Portal, via an authorised agent, or via UAC (UAC required if completing an Australian Year 12; IB students in Australia may use UAC or apply direct) | W17: CRICOS 088843G. Official title: Bachelor of Science (Advanced Mathematics) (Honours), program 3956, UAC 429300. Commencing Terms 1, 2 & 3. 4-year degree with integrated Honours. | X17: Confirmed | Y17: Source URL dead - degree is the 4-year (Honours) program, not 3 years as sheet states; sheet IB 39-42 vs published 34.0; sheet CBSE 94%+ vs 81.0; sheet ISC 90%+ vs 89.0; sheet fee 54,000 vs 61,000 | Z17: https://www.unsw.edu.au/study/undergraduate/bachelor-of-science-advanced-mathematics-honours | AA17: All India Senior School Certificate (CBSE) 81.0; International Baccalaureate Diploma (IB) 34.0; 2026 Indicative First Year Fee $61,000* | AB17: 13 September 2026 | AC17: yes | AD17: Pave verification, web-checked | AE17: Academic transcripts/certificates, English evidence, passport; personal statement for some scholarships; submit via UNSW Applicant Portal | AF17: UNSW publishes per-round offer schedules rather than a single closing date (unsw.edu.au/study/international-students/admissions-info, checked 13 September 2026); final T1 2027 round not yet listed, so deadline_iso_close left blank | AG17: 2026 | AH17: A non-refundable application fee of $150 AUD may be payable via the UNSW Applicant Portal (credit card; some exclusions) | AJ17: 81.0 (2026 international direct entry). CBSE basis: average percentage across English or Hindi plus best four remaining subjects (range marks use mid-point) | ISC: 89.0 (2026 international direct entry)
A18: AU-017 | B18: UNSW Sydney | C18: Australia | D18: Bachelor of Laws (LLB) | E18: Bachelor | F18: https://www.unsw.edu.au/study/undergraduate/bachelor-of-arts-law | G18: Go8 / Top Research | H18: English | I18: 5 | J18: India State Board 98.0 (MH/KA/TN only) | K18: 36.0 international direct entry requirement (2026, BA/Law); domestic 2026 LSR 97.8 + LAT (IB guide 42 + LAT) | L18: 15.0 points international direct entry (2026). A-level basis: minimum two A2 subjects; score aggregated from best 2-4 A2 subjects, A*=6 A=5 B=4 C=3 D=2 E=1 | M18: 85.0 (2026 international direct entry). CBSE basis: average percentage across English or Hindi plus best four remaining subjects (range marks use mid-point) | N18: 92.0 (2026 international direct entry) | O18: Rank/score-based for internationals (no LAT); assumed knowledge: none | P18: IELTS 7.0 overall (min 6.0 in each subtest) - Law & Justice requirement (higher requirement applies to cross-faculty doubles) | Q18: LAT (Law Admission Test) applies to domestic UAC applicants only - international applicants are not eligible to sit the LAT and are assessed on academic results | R18: Rolling offer rounds. Published Term 1 2027 undergraduate international round deadlines: 14 May 2026, 16 July 2026, 20 August 2026, 24 September 2026 (completed-application deadlines per round); later rounds published progressively | S18: A$52,500 indicative first year fee 2026 (BA/Law) | T18: International Scientia Coursework Scholarship (full tuition or $20,000/year); UNSW International Student Award (20% tuition contribution, 500-word personal statement) | U18: Australian Student visa (subclass 500) after acceptance and CoE; OSHC required | V18: Direct via the UNSW Applicant Portal, via an authorised agent, or via UAC (UAC required if completing an Australian Year 12; IB students in Australia may use UAC or apply direct). Domestic double-law applications go through UAC code 426000 | W18: CRICOS 005947G (BA/Law). Program 4782, UAC 426000. Term 1 intake only. UNSW does NOT offer a standalone undergraduate LLB - law is taken as a 5-year double degree (Arts/Commerce/Economics/Science etc. + Law); BA/Law used as reference combination. | X18: Confirmed | Y18: Sheet describes a 4-year standalone LLB that does not exist (dead URL; UNSW law is 5-year double degree, Term 1 only); sheet IB 41-45 vs published international direct entry 36.0; sheet IELTS 7.0/6.5 vs published 7.0/6.0; sheet CBSE 95%+ vs 85.0; sheet ISC 92%+ matches 92.0; sheet fee 55,000 vs 52,500 (BA/Law) | Z18: https://www.unsw.edu.au/study/undergraduate/bachelor-of-arts-law | AA18: All India Senior School Certificate (CBSE) 85.0; International Baccalaureate Diploma (IB) 36.0; 2026 Indicative First Year Fee $52,500* | AB18: 13 September 2026 | AC18: yes | AD18: Pave verification, web-checked | AE18: Academic transcripts/certificates, English evidence, passport; personal statement for some scholarships; submit via UNSW Applicant Portal | AF18: UNSW publishes per-round offer schedules rather than a single closing date (unsw.edu.au/study/international-students/admissions-info, checked 13 September 2026); final T1 2027 round not yet listed, so deadline_iso_close left blank | AG18: 2026 | AH18: A non-refundable application fee of $150 AUD may be payable via the UNSW Applicant Portal (credit card; some exclusions) | AJ18: 85.0 (2026 international direct entry). CBSE basis: average percentage across English or Hindi plus best four remaining subjects (range marks use mid-point) | ISC: 92.0 (2026 international direct entry)
A19: AU-018 | B19: UNSW Sydney | C19: Australia | D19: Bachelor of Design | E19: Bachelor | F19: https://www.unsw.edu.au/study/undergraduate/bachelor-of-design1 | G19: Go8 / Top Research | H19: English | I19: 3 | J19: India State Board 87.0 (MH/KA/TN only) | K19: 29.0 international direct entry requirement (2026); domestic 2026 LSR 83.0 (IB guide 31.0) | L19: 10.0 points international direct entry (2026). A-level basis: minimum two A2 subjects; score aggregated from best 2-4 A2 subjects, A*=6 A=5 B=4 C=3 D=2 E=1 | M19: 75.0 (2026 international direct entry). CBSE basis: average percentage across English or Hindi plus best four remaining subjects (range marks use mid-point) | N19: 83.0 (2026 international direct entry) | O19: Rank/score-based; no portfolio or interview published | P19: IELTS 6.5 overall (min 6.0 in each subtest) - standard UNSW requirement | Q19: None - no portfolio requirement published; entry is on ATAR/equivalent rank plus English ('you'll need to meet the relevant entry criteria - including the published ATAR cut-off or equivalent, English language requirements'). Assumed knowledge: none | R19: Rolling offer rounds. Published Term 1 2027 undergraduate international round deadlines: 14 May 2026, 16 July 2026, 20 August 2026, 24 September 2026 (completed-application deadlines per round); later rounds published progressively | S19: A$49,500 indicative first year fee 2026 | T19: International Scientia Coursework Scholarship (full tuition or $20,000/year); UNSW International Student Award (20% tuition contribution, 500-word personal statement) | U19: Australian Student visa (subclass 500) after acceptance and CoE; OSHC required | V19: Direct via the UNSW Applicant Portal, via an authorised agent, or via UAC (UAC required if completing an Australian Year 12; IB students in Australia may use UAC or apply direct) | W19: CRICOS 110651E. Program 4825, UAC 421050. Commencing Terms 1, 2 & 3. Source URL redirects to bachelor-of-design1. This is UNSW School of Art & Design's Bachelor of Design (not the Built Environment architecture degree - architecture is the separate Bachelor of Architectural Studies). | X19: Confirmed | Y19: Sheet 'Portfolio required' has no published basis - entry is rank-based with no portfolio mentioned; sheet IB 32-36 vs published 29.0; sheet CBSE 85%+ vs 75.0; sheet ISC 78%+ vs 83.0; sheet fee 52,000 vs 49,500; sheet notes describe Built Environment/architecture streams, but architecture is a separate degree | Z19: https://www.unsw.edu.au/study/undergraduate/bachelor-of-design1 | AA19: All India Senior School Certificate (CBSE) 75.0; International Baccalaureate Diploma (IB) 29.0; 2026 Indicative First Year Fee $49,500* | AB19: 13 September 2026 | AC19: yes | AD19: Pave verification, web-checked | AE19: Academic transcripts/certificates, English evidence, passport; personal statement for some scholarships; submit via UNSW Applicant Portal | AF19: UNSW publishes per-round offer schedules rather than a single closing date (unsw.edu.au/study/international-students/admissions-info, checked 13 September 2026); final T1 2027 round not yet listed, so deadline_iso_close left blank | AG19: 2026 | AH19: A non-refundable application fee of $150 AUD may be payable via the UNSW Applicant Portal (credit card; some exclusions) | AJ19: 75.0 (2026 international direct entry). CBSE basis: average percentage across English or Hindi plus best four remaining subjects (range marks use mid-point) | ISC: 83.0 (2026 international direct entry)
A20: AU-019 | B20: Australian National University (ANU) | C20: Australia | D20: Bachelor of Commerce | E20: Bachelor | F20: https://programsandcourses.anu.edu.au/program/BCOMM | G20: Go8 / Top Research | H20: English | I20: 3 | K20: 30 | L20: Not published as A-level grades; ANU rank 80 required (see notes) | M20: 14.0/20 (ANU rank 80 row; ANU converts CBSE (AISSC) on a 20-point scale: marks in English or Hindi plus best 4 externally examined subjects (A1=4, A2=3.5, B1=3 ... D2=0.5) - NOT a percentage) | N20: 84 average (ANU rank 80 row; ISC: average of marks in English and best 3 externally examined subjects) | O20: ATAR 80 guaranteed entry; minimum consideration rank 70. Prerequisite: Mathematical Methods (major)/equivalent assumed | P20: IELTS Academic 6.5 overall, no band below 6.0 (Reading/Writing/Listening/Speaking 6.0); TOEFL iBT 81 overall (R16 W19 L16 S19) for study from 1 Jan 2027 — university-wide UG policy ANUP_000408, no higher requirement listed for Law | Q20: None published for this course | R20: Semester 1 2027 intake (Feb): applications close 15 December 2026; Semester 2 2027 intake (Jul): close 15 May 2027 | S20: AUD 57,640 per year | T20: Not verified this pass; sheet's 'Chancellor's International Scholarship (75%)' unconfirmed | U20: Student visa (subclass 500) after acceptance - standard Australian process | V20: Direct online application via ANU (AUD$150 fee per application); current Year 12/IB/NCEA students apply via UAC | W20: CRICOS 002289F. Intakes Feb (S1) and Jul (S2). Maths prerequisite: 'Mathematical Methods (Major)/Further Mathematics/Specialist Mathematics (major)' or HSC Mathematics Advanced equivalent | X20: Confirmed | Y20: Sheet tuition 'AUD 45,000-50,000' wrong (57,640); sheet CBSE '83%+' wrong format - ANU uses a 20-point grade scale (14.0 needed); sheet ISC '75%+' wrong (84 needed); sheet deadline '15 May' is the S2 close only - S1 closes 15 Dec | Z20: https://programsandcourses.anu.edu.au/program/BCOMM | AA20: International Baccalaureate: 30; ATAR: 80; indicative international annual fee $57,640.00; CRICOS 002289F | AB20: 13 September 2026 | AC20: yes | AD20: Pave verification, web-checked | AE20: Academic transcripts, evidence of English proficiency, passport; per ANU international application portal | AF20: S1 2027 close published; S2 2027 close 15 May 2027 also published | AG20: 2027 (current catalogue year) | AH20: AUD 150 | AI20: 2026-12-15 | AJ20: 14.0/20 (ANU rank 80 row; ANU converts CBSE (AISSC) on a 20-point scale: marks in English or Hindi plus best 4 externally examined subjects (A1=4, A2=3.5, B1=3 ... D2=0.5) - NOT a percentage) | ISC: 84 average (ANU rank 80 row; ISC: average of marks in English and best 3 externally examined subjects)
A21: AU-020 | B21: Australian National University (ANU) | C21: Australia | D21: Bachelor of International Relations | E21: Bachelor | F21: https://programsandcourses.anu.edu.au/program/bir | G21: Go8 / Top Research | H21: English | I21: 3 | K21: 33 | L21: Not published as A-level grades; ANU rank 85 required | M21: 15.5/20 (ANU rank 85 row; ANU converts CBSE (AISSC) on a 20-point scale: marks in English or Hindi plus best 4 externally examined subjects (A1=4, A2=3.5, B1=3 ... D2=0.5) - NOT a percentage) | N21: 87 average (ANU rank 85 row) | O21: ATAR 85; no admissions test | P21: IELTS Academic 6.5 overall, no band below 6.0 (Reading/Writing/Listening/Speaking 6.0); TOEFL iBT 81 overall (R16 W19 L16 S19) for study from 1 Jan 2027 — university-wide UG policy ANUP_000408, no higher requirement listed for Law | Q21: None published for this course | R21: Semester 1 2027 intake (Feb): applications close 15 December 2026; Semester 2 2027 intake (Jul): close 15 May 2027 | S21: AUD 54,540 per year | T21: Not verified this pass; sheet's 'Chancellor's International Scholarship (75%)' unconfirmed | U21: Student visa (subclass 500) after acceptance - standard Australian process | V21: Direct online application via ANU (AUD$150 fee per application); current Year 12/IB/NCEA students apply via UAC | W21: CRICOS 073992F. 144 units. Program code is BIR (not BINTL). Semester 2 commencement possible with course-availability restrictions | X21: Confirmed | Y21: Sheet course_url dead; sheet IB 32 wrong (33); sheet CBSE 85%/ISC 78% wrong format and values; sheet tuition AUD 43,000-48,000 wrong (54,540) | Z21: https://programsandcourses.anu.edu.au/program/bir | AA21: CRICOS 073992F; IB 33; ATAR 85; international annual fee $54,540.00 | AB21: 13 September 2026 | AD21: Pave verification, web-checked | AE21: Academic transcripts, evidence of English proficiency, passport; per ANU international application portal | AF21: S1 2027 close published | AG21: 2027 (current catalogue year) | AH21: AUD 150 | AI21: 2026-12-15 | AJ21: 15.5/20 (ANU rank 85 row; ANU converts CBSE (AISSC) on a 20-point scale: marks in English or Hindi plus best 4 externally examined subjects (A1=4, A2=3.5, B1=3 ... D2=0.5) - NOT a percentage) | ISC: 87 average (ANU rank 85 row)
A22: AU-021 | B22: Australian National University (ANU) | C22: Australia | D22: Bachelor of Laws (LLB) | E22: Bachelor | F22: https://programsandcourses.anu.edu.au/program/allb | G22: Go8 / Top Research | H22: English | I22: 4 | K22: 41 | L22: Not published as A-level grades; ANU rank 97 required | M22: 19.0/20 (ANU rank 97 row; ANU converts CBSE (AISSC) on a 20-point scale: marks in English or Hindi plus best 4 externally examined subjects (A1=4, A2=3.5, B1=3 ... D2=0.5) - NOT a percentage) | N22: 95 average (ANU rank 97 row) | O22: ATAR 97 guaranteed; minimum consideration rank 87. Applicants who already hold a bachelor degree are ineligible (apply for JD instead) | P22: IELTS Academic 6.5 overall, no band below 6.0 (Reading/Writing/Listening/Speaking 6.0); TOEFL iBT 81 overall (R16 W19 L16 S19) for study from 1 Jan 2027 — university-wide UG policy ANUP_000408, no higher requirement listed for Law - note: ANU policy lists the SAME 6.5/6.0 for Law, not 7.0 | Q22: None published for this course | R22: Semester 1 2027 intake (Feb): applications close 15 December 2026; Semester 2 2027 intake (Jul): close 15 May 2027 | S22: AUD 54,540 per year | T22: Not verified this pass; sheet's 'Chancellor's International Scholarship (75%)' unconfirmed | U22: Student visa (subclass 500) after acceptance - standard Australian process | V22: Direct online application via ANU (AUD$150 fee per application); current Year 12/IB/NCEA students apply via UAC | W22: Actual award is Bachelor of Laws (Honours), program code ALLB. CRICOS 085042J. 192 units | X22: Confirmed | Y22: Sheet course_url dead; sheet IB 38-42 low end wrong (41); sheet IELTS 7.0/6.5 not supported by ANU policy (uniform 6.5/6.0); sheet CBSE 93%/ISC 88% wrong format/values; sheet tuition 45,000-52,000 wrong (54,540) | Z22: https://programsandcourses.anu.edu.au/program/allb | AA22: CRICOS 085042J; IB 41; ATAR 97 guaranteed entry, minimum consideration 87; international annual fee $54,540.00 | AB22: 13 September 2026 | AD22: Pave verification, web-checked | AE22: Academic transcripts, evidence of English proficiency, passport; per ANU international application portal | AF22: S1 2027 close published | AG22: 2027 (current catalogue year) | AH22: AUD 150 | AI22: 2026-12-15 | AJ22: 19.0/20 (ANU rank 97 row; ANU converts CBSE (AISSC) on a 20-point scale: marks in English or Hindi plus best 4 externally examined subjects (A1=4, A2=3.5, B1=3 ... D2=0.5) - NOT a percentage) | ISC: 95 average (ANU rank 97 row)
A23: AU-022 | B23: Australian National University (ANU) | C23: Australia | D23: Bachelor of Science (Advanced) | E23: Bachelor | F23: https://programsandcourses.anu.edu.au/program/ascad | G23: Go8 / Top Research | H23: English | I23: 4 (3 years coursework + research honours year) | K23: 35 | L23: Not published as A-level grades; ANU rank 90 required | M23: 17.0/20 (ANU rank 90 row; ANU converts CBSE (AISSC) on a 20-point scale: marks in English or Hindi plus best 4 externally examined subjects (A1=4, A2=3.5, B1=3 ... D2=0.5) - NOT a percentage) | N23: 90 average (ANU rank 90 row) | O23: ATAR 90 guaranteed; minimum consideration unadjusted rank 75. No formal program prerequisites; specific courses assume ACT/NSW maths and chemistry majors or bridging | P23: IELTS Academic 6.5 overall, no band below 6.0 (Reading/Writing/Listening/Speaking 6.0); TOEFL iBT 81 overall (R16 W19 L16 S19) for study from 1 Jan 2027 — university-wide UG policy ANUP_000408, no higher requirement listed for Law | Q23: None published for this course | R23: Semester 1 2027 intake (Feb): applications close 15 December 2026; Semester 2 2027 intake (Jul): close 15 May 2027 | S23: AUD 57,640 per year | T23: Not verified this pass; sheet's 'Chancellor's International Scholarship (75%)' unconfirmed | U23: Student visa (subclass 500) after acceptance - standard Australian process | V23: Direct online application via ANU (AUD$150 fee per application); current Year 12/IB/NCEA students apply via UAC | W23: Actual award is Bachelor of Science (Advanced) (Honours), program code ASCAD, 192 units. CRICOS 065138M | X23: Confirmed | Y23: Sheet duration 3 wrong (4 - honours embedded); sheet IB 32 wrong (35); sheet CBSE 85%/ISC 78% wrong format/values; sheet tuition 44,000-50,000 wrong (57,640) | Z23: https://programsandcourses.anu.edu.au/program/ascad | AA23: Length 4 year full-time; International Baccalaureate: 35; ATAR: 90; indicative international annual fee $57,640.00 (2027); CRICOS 065138M | AB23: 13 September 2026 | AD23: Pave verification, web-checked | AE23: Academic transcripts, evidence of English proficiency, passport; per ANU international application portal | AF23: S1 2027 close published | AG23: 2027 (page notes current year 2027) | AH23: AUD 150 | AI23: 2026-12-15 | AJ23: 17.0/20 (ANU rank 90 row; ANU converts CBSE (AISSC) on a 20-point scale: marks in English or Hindi plus best 4 externally examined subjects (A1=4, A2=3.5, B1=3 ... D2=0.5) - NOT a percentage) | ISC: 90 average (ANU rank 90 row)
A24: AU-023 | B24: Australian National University (ANU) | C24: Australia | D24: Bachelor of Philosophy (PhB) | E24: Bachelor | F24: https://programsandcourses.anu.edu.au/program/aphsc | G24: Go8 / Top Research | H24: English | I24: 4 | K24: 43 | L24: Not published as A-level grades; ANU rank 99 required | M24: 20.0/20 (ANU rank 99 row; ANU converts CBSE (AISSC) on a 20-point scale: marks in English or Hindi plus best 4 externally examined subjects (A1=4, A2=3.5, B1=3 ... D2=0.5) - NOT a percentage) | N24: 96 average (ANU rank 99 row) | O24: ATAR 99 guaranteed entry band; minimum consideration rank 94; compulsory supplementary application form; suitability assessment | P24: IELTS Academic 6.5 overall, no band below 6.0 (Reading/Writing/Listening/Speaking 6.0); TOEFL iBT 81 overall (R16 W19 L16 S19) for study from 1 Jan 2027 — university-wide UG policy ANUP_000408, no higher requirement listed for Law | Q24: None published for this course | R24: Semester 1 2027 intake (Feb): applications close 15 December 2026; Semester 2 2027 intake (Jul): close 15 May 2027 | S24: AUD 57,640 per year | T24: Not verified this pass; sheet's 'Chancellor's International Scholarship (75%)' unconfirmed | U24: Student visa (subclass 500) after acceptance - standard Australian process | V24: Direct online application via ANU (AUD$150 fee per application); current Year 12/IB/NCEA students apply via UAC | W24: Bachelor of Philosophy (Honours) - Science, program code APHSC, CRICOS 043746B, 192 units. Sheet claim 'fully funded scholarship including fees and stipend' NOT found on the program page - do not repeat without source | X24: Confirmed | Y24: Sheet IB 42 low end wrong (43); sheet CBSE 96%/ISC 93% wrong format/values; sheet tuition 45,000-50,000 wrong (57,640); funded-scholarship claim unverified | Z24: https://programsandcourses.anu.edu.au/program/aphsc | AA24: IB 43; ATAR 99 (minimum consideration 94); 'Bachelor of Philosophy (Honours) - Science Supplementary Form' is 'compulsory for all applicants'; fee $57,640.00; CRICOS 043746B | AB24: 13 September 2026 | AD24: Pave verification, web-checked | AE24: Academic transcripts, evidence of English proficiency, passport; per ANU international application portal; plus 'Bachelor of Philosophy (Honours) - Science Supplementary Form' (compulsory for all applicants) | AF24: S1 2027 close published; supplementary form has program-specific timing | AG24: 2027 (current catalogue year) | AH24: AUD 150 | AI24: 2026-12-15 | AJ24: 20.0/20 (ANU rank 99 row; ANU converts CBSE (AISSC) on a 20-point scale: marks in English or Hindi plus best 4 externally examined subjects (A1=4, A2=3.5, B1=3 ... D2=0.5) - NOT a percentage) | ISC: 96 average (ANU rank 99 row)
A25: AU-024 | B25: Australian National University (ANU) | C25: Australia | D25: Bachelor of Politics, Philosophy & Economics | E25: Bachelor | F25: https://programsandcourses.anu.edu.au/program/BPPE | G25: Go8 / Top Research | H25: English | I25: 3 | K25: 38 | L25: Not published as A-level grades; ANU rank 94 required | M25: 18.5/20 (ANU rank 94 row; ANU converts CBSE (AISSC) on a 20-point scale: marks in English or Hindi plus best 4 externally examined subjects (A1=4, A2=3.5, B1=3 ... D2=0.5) - NOT a percentage) | N25: ANU table row for rank 94 not cleanly published; adjacent rows: rank 92 = 92, rank 95 = 93 | O25: ATAR 94. 'There are no formal program prerequisites'; advanced-level mathematics assumed knowledge | P25: IELTS Academic 6.5 overall, no band below 6.0 (Reading/Writing/Listening/Speaking 6.0); TOEFL iBT 81 overall (R16 W19 L16 S19) for study from 1 Jan 2027 — university-wide UG policy ANUP_000408, no higher requirement listed for Law | Q25: None published for this course | R25: Semester 1 2027 intake (Feb): applications close 15 December 2026; Semester 2 2027 intake (Jul): close 15 May 2027 | S25: AUD 57,640 per year | T25: Not verified this pass; sheet's 'Chancellor's International Scholarship (75%)' unconfirmed | U25: Student visa (subclass 500) after acceptance - standard Australian process | V25: Direct online application via ANU (AUD$150 fee per application); current Year 12/IB/NCEA students apply via UAC | W25: CRICOS 076183D. Semester 2 commencement possible with restrictions | X25: Confirmed | Y25: Sheet ATAR 88 wrong (94); sheet IB 33-37 wrong (38); sheet CBSE 87%/ISC 80% wrong format/values; sheet tuition 43,000-48,000 wrong (57,640) | Z25: https://programsandcourses.anu.edu.au/program/BPPE | AA25: CRICOS 076183D; IB 38; ATAR 94; indicative international annual fee $57,640.00; 'There are no formal program prerequisites' | AB25: 13 September 2026 | AC25: yes | AD25: Pave verification, web-checked | AE25: Academic transcripts, evidence of English proficiency, passport; per ANU international application portal | AF25: S1 2027 close published | AG25: 2027 (current catalogue year) | AH25: AUD 150 | AI25: 2026-12-15 | AJ25: 18.5/20 (ANU rank 94 row; ANU converts CBSE (AISSC) on a 20-point scale: marks in English or Hindi plus best 4 externally examined subjects (A1=4, A2=3.5, B1=3 ... D2=0.5) - NOT a percentage) | ISC: ANU table row for rank 94 not cleanly published; adjacent rows: rank 92 = 92, rank 95 = 93
A26: AU-025 | B26: Monash University | C26: Australia | D26: Bachelor of Commerce | E26: Bachelor | F26: https://www.monash.edu/study/courses/find-a-course/commerce-b2001 | G26: Go8 / Top Research | H26: English | I26: 3 | K26: 31 | L26: 11 points from best 3 A Levels (A*=5+1 bonus, A=5, B=4, C=3, D=2, E=1) | M26: 81% - Monash India method: 'Overall average of the best four academic subjects' on the official CBSE Marks Statement / ISC Statement of Marks | N26: 76% - Monash India method: 'Overall average of the best four academic subjects' on the official CBSE Marks Statement / ISC Statement of Marks | O26: ATAR 87.5 equivalent. Prerequisite subjects: English and Mathematics (course checklist); no admissions test | P26: IELTS Academic 6.5 overall, minimum band scores L6.0 R6.0 W6.0 S6.0 (Monash English Level A, shown on the course page); equivalent approved tests accepted | Q26: None published for this course | R26: No fixed international closing date published; direct applications assessed year-round for February (S1), July (S2) intakes | S26: A$59,140 per 48 credit points (standard year) | T26: Monash states 'over 360 types of scholarships' and International Study Grants 'valued at up to $10,000' (course pages); named-scholarship details not verified this pass | U26: Student visa (subclass 500) - 'If you are an international student, you will need a student visa (subclass 500) to study at Monash' | V26: Apply directly to Monash online (A$125 applicant fee, or a waiver code); VTAC only if completing Australian Year 12 anywhere or IB in Australia/NZ | W26: CRICOS 013382G. Intakes: February (S1), July (S2) and November (Actuarial Studies unavailable in November). Clayton campus | X26: Confirmed | Y26: Sheet fee upper 'AUD 55,900' wrong for 2027 (A$59,140); sheet 'Rolling' deadline confirmed correct | Z26: https://www.monash.edu/study/courses/find-a-course/commerce-b2001?international=true | AA26: 2027 entry scores: ATAR 87.5; GCE A Level 11; International Baccalaureate Diploma Programme 31; All India Senior School Certificate Examination 81%; Indian School Certificate Examination 76%. 'The fees for 2027 are: A$59,140'. CRICOS code: 013382G | AB26: 13 September 2026 | AC26: yes | AD26: Pave verification, web-checked | AE26: Certified transcripts, passport copy, evidence of English, translations where needed, A$125 applicant fee (per monash.edu/admissions/apply/online) | AF26: 2027 entry requirements shown; no fixed close date published (checked 13 Sep 2026) | AG26: 2027 | AH26: A$125 | AJ26: 81% - Monash India method: 'Overall average of the best four academic subjects' on the official CBSE Marks Statement / ISC Statement of Marks | ISC: 76% - Monash India method: 'Overall average of the best four academic subjects' on the official CBSE Marks Statement / ISC Statement of Marks
A27: AU-026 | B27: Monash University | C27: Australia | D27: Bachelor of Science | E27: Bachelor | F27: https://www.monash.edu/study/courses/find-a-course/science-s2000 | G27: Go8 / Top Research | H27: English | I27: 3 | K27: 28 | L27: 9 points from best 3 A Levels | M27: 75% - Monash India method: 'Overall average of the best four academic subjects' on the official CBSE Marks Statement / ISC Statement of Marks | N27: 70% - Monash India method: 'Overall average of the best four academic subjects' on the official CBSE Marks Statement / ISC Statement of Marks | O27: ATAR 80 equivalent. Prerequisites: English, Mathematics and a Science (course checklist) | P27: IELTS Academic 6.5 overall, minimum band scores L6.0 R6.0 W6.0 S6.0 (Monash English Level A, shown on the course page); equivalent approved tests accepted | Q27: None published for this course | R27: No fixed international closing date published; direct applications assessed year-round for February (S1), July (S2) intakes | S27: A$60,040 per 48 credit points | T27: Monash states 'over 360 types of scholarships' and International Study Grants 'valued at up to $10,000' (course pages); named-scholarship details not verified this pass | U27: Student visa (subclass 500) - 'If you are an international student, you will need a student visa (subclass 500) to study at Monash' | V27: Apply directly to Monash online (A$125 applicant fee, or a waiver code); VTAC only if completing Australian Year 12 anywhere or IB in Australia/NZ | W27: CRICOS 017092G. Intakes Feb (S1), Jul (S2); Malaysia campus October intake also exists | X27: Confirmed | Y27: Sheet CBSE 78% wrong (75%); sheet ISC 72% wrong (70%); sheet tuition 50,000-58,000 vs actual 60,040 for 2027 | Z27: https://www.monash.edu/study/courses/find-a-course/science-s2000?international=true | AA27: 2027 entry scores: ATAR 80; GCE A Level 9; IB 28; AISSCE (CBSE) 75%; ISC 70%. 'The fees for 2027 are: A$60,040'. CRICOS code: 017092G | AB27: 13 September 2026 | AC27: yes | AD27: Pave verification, web-checked | AE27: Certified transcripts, passport copy, evidence of English, translations where needed, A$125 applicant fee (per monash.edu/admissions/apply/online) | AF27: 2027 requirements shown; no fixed close date published | AG27: 2027 | AH27: A$125 | AJ27: 75% - Monash India method: 'Overall average of the best four academic subjects' on the official CBSE Marks Statement / ISC Statement of Marks | ISC: 70% - Monash India method: 'Overall average of the best four academic subjects' on the official CBSE Marks Statement / ISC Statement of Marks
A28: AU-027 | B28: Monash University | C28: Australia | D28: Bachelor of Engineering (Honours) | E28: Bachelor | F28: https://www.monash.edu/study/courses/find-a-course/engineering-e3001 | G28: Go8 / Top Research | H28: English | I28: 4 | J28: Prerequisite subjects: English, Mathematics and Science (course checklist) | K28: 30 | L28: 10 points from best 3 A Levels | M28: 80% - Monash India method: 'Overall average of the best four academic subjects' on the official CBSE Marks Statement / ISC Statement of Marks | N28: 75% - Monash India method: 'Overall average of the best four academic subjects' on the official CBSE Marks Statement / ISC Statement of Marks | O28: ATAR 85 equivalent; common first year then specialisation; no admissions test | P28: IELTS Academic 6.5 overall, minimum band scores L6.0 R6.0 W6.0 S6.0 (Monash English Level A, shown on the course page); equivalent approved tests accepted | Q28: None published for this course | R28: No fixed international closing date published; direct applications assessed year-round for February (S1), July (S2) intakes | S28: A$63,040 per 48 credit points | T28: Monash states 'over 360 types of scholarships' and International Study Grants 'valued at up to $10,000' (course pages); named-scholarship details not verified this pass | U28: Student visa (subclass 500) - 'If you are an international student, you will need a student visa (subclass 500) to study at Monash' | V28: Apply directly to Monash online (A$125 applicant fee, or a waiver code); VTAC only if completing Australian Year 12 anywhere or IB in Australia/NZ | W28: CRICOS 001722B. Intakes Feb (S1), Jul (S2); Biomedical Engineering not offered in July | X28: Confirmed | Y28: Sheet URL dead; sheet ATAR 93+/IB 36-40/A-level AAB/CBSE 90%/ISC 85% all wrong - published 2027 scores are much lower (ATAR 85, IB 30, CBSE 80%); sheet tuition 54,000-62,000 vs actual 63,040 | Z28: https://www.monash.edu/study/courses/find-a-course/engineering-e3001?international=true | AA28: 2027 entry scores: ATAR 85; GCE A Level 10; IB 30; AISSCE (CBSE) 80%; ISC 75%. 'The fees for 2027 are: A$63,040'. CRICOS code: 001722B | AB28: 13 September 2026 | AD28: Pave verification, web-checked | AE28: Certified transcripts, passport copy, evidence of English, translations where needed, A$125 applicant fee (per monash.edu/admissions/apply/online) | AF28: 2027 requirements shown; no fixed close date published | AG28: 2027 | AH28: A$125 | AJ28: 80% - Monash India method: 'Overall average of the best four academic subjects' on the official CBSE Marks Statement / ISC Statement of Marks | ISC: 75% - Monash India method: 'Overall average of the best four academic subjects' on the official CBSE Marks Statement / ISC Statement of Marks
A29: AU-028 | B29: Monash University | C29: Australia | D29: Bachelor of Computer Science | E29: Bachelor | F29: https://www.monash.edu/study/courses/find-a-course/computer-science-c2001 | G29: Go8 / Top Research | H29: English | I29: 3 | J29: Prerequisite subjects: English and Mathematics (course checklist) | K29: 28 | L29: 9 points from best 3 A Levels | M29: 75% - Monash India method: 'Overall average of the best four academic subjects' on the official CBSE Marks Statement / ISC Statement of Marks | N29: 70% - Monash India method: 'Overall average of the best four academic subjects' on the official CBSE Marks Statement / ISC Statement of Marks | O29: ATAR 80 equivalent; no admissions test | P29: IELTS Academic 6.5 overall, minimum band scores L6.0 R6.0 W6.0 S6.0 (Monash English Level A, shown on the course page); equivalent approved tests accepted | Q29: None published for this course | R29: No fixed international closing date published; direct applications assessed year-round for February (S1), July (S2) intakes | S29: A$58,940 per 48 credit points | T29: Monash states 'over 360 types of scholarships' and International Study Grants 'valued at up to $10,000' (course pages); named-scholarship details not verified this pass | U29: Student visa (subclass 500) - 'If you are an international student, you will need a student visa (subclass 500) to study at Monash' | V29: Apply directly to Monash online (A$125 applicant fee, or a waiver code); VTAC only if completing Australian Year 12 anywhere or IB in Australia/NZ | W29: CRICOS 079336A. Intakes Feb (S1), Jul (S2). Clayton (Malaysia campus also offered) | X29: Confirmed | Y29: Sheet ATAR 90/IB 34-38/A-level ABB/CBSE 88%/ISC 82% all wrong - published 2027 scores are ATAR 80, IB 28, CBSE 75%, ISC 70%; sheet tuition 52,000-58,000 vs actual 58,940 | Z29: https://www.monash.edu/study/courses/find-a-course/computer-science-c2001?international=true | AA29: 2027 entry scores: ATAR 80; GCE A Level 9; IB 28; AISSCE (CBSE) 75%; ISC 70%. 'The fees for 2027 are: A$58,940'. CRICOS code: 079336A | AB29: 13 September 2026 | AC29: yes | AD29: Pave verification, web-checked | AE29: Certified transcripts, passport copy, evidence of English, translations where needed, A$125 applicant fee (per monash.edu/admissions/apply/online) | AF29: 2027 requirements shown; no fixed close date published | AG29: 2027 | AH29: A$125 | AJ29: 75% - Monash India method: 'Overall average of the best four academic subjects' on the official CBSE Marks Statement / ISC Statement of Marks | ISC: 70% - Monash India method: 'Overall average of the best four academic subjects' on the official CBSE Marks Statement / ISC Statement of Marks
A30: AU-029 | B30: Monash University | C30: Australia | D30: Bachelor of Arts | E30: Bachelor | F30: https://www.monash.edu/study/courses/find-a-course/arts-a2000 | G30: Go8 / Top Research | H30: English | I30: 3 | K30: 26 | L30: 8 points from best 3 A Levels | M30: 70% - Monash India method: 'Overall average of the best four academic subjects' on the official CBSE Marks Statement / ISC Statement of Marks | N30: 65% - Monash India method: 'Overall average of the best four academic subjects' on the official CBSE Marks Statement / ISC Statement of Marks | O30: ATAR 75 equivalent; English prerequisite; no admissions test | P30: IELTS Academic 6.5 overall, minimum band scores L6.0 R6.0 W6.0 S6.0 (Monash English Level A, shown on the course page); equivalent approved tests accepted | Q30: None published for this course | R30: No fixed international closing date published; direct applications assessed year-round for February (S1), July (S2) intakes | S30: A$47,340 per 48 credit points | T30: Monash states 'over 360 types of scholarships' and International Study Grants 'valued at up to $10,000' (course pages); named-scholarship details not verified this pass | U30: Student visa (subclass 500) - 'If you are an international student, you will need a student visa (subclass 500) to study at Monash' | V30: Apply directly to Monash online (A$125 applicant fee, or a waiver code); VTAC only if completing Australian Year 12 anywhere or IB in Australia/NZ | W30: CRICOS 075404D. Intakes Feb (S1), Jul (S2). Caulfield and Clayton campuses | X30: Confirmed | Y30: Sheet ATAR 68 wrong (75); sheet CBSE 75% wrong (70%); sheet ISC 68% wrong (65%) | Z30: https://www.monash.edu/study/courses/find-a-course/arts-a2000?international=true | AA30: 2027 entry scores: ATAR 75; GCE A Level 8; IB 26; AISSCE (CBSE) 70%; ISC 65%. 'The fees for 2027 are: A$47,340'. CRICOS code: 075404D | AB30: 13 September 2026 | AC30: yes | AD30: Pave verification, web-checked | AE30: Certified transcripts, passport copy, evidence of English, translations where needed, A$125 applicant fee (per monash.edu/admissions/apply/online) | AF30: 2027 requirements shown; no fixed close date published | AG30: 2027 | AH30: A$125 | AJ30: 70% - Monash India method: 'Overall average of the best four academic subjects' on the official CBSE Marks Statement / ISC Statement of Marks | ISC: 65% - Monash India method: 'Overall average of the best four academic subjects' on the official CBSE Marks Statement / ISC Statement of Marks
A31: AU-030 | B31: Monash University | C31: Australia | D31: Bachelor of Law (LLB) | E31: Bachelor | F31: https://www.monash.edu/study/courses/find-a-course/laws-l3001 | G31: Go8 / Top Research | H31: English | I31: 4.25 (may be accelerated to 4; part-time available) | K31: 36 | L31: 13 points from best 3 A Levels | M31: 85% - Monash India method: 'Overall average of the best four academic subjects' on the official CBSE Marks Statement / ISC Statement of Marks | N31: 80% - Monash India method: 'Overall average of the best four academic subjects' on the official CBSE Marks Statement / ISC Statement of Marks | O31: ATAR 95 equivalent; no LSAT/LNAT-style admissions test for direct entry | P31: IELTS Academic 7.0 overall, minimum bands L6.5 R6.5 W6.5 S6.5 (Monash English Level C, shown on the course page) | Q31: None published for this course | R31: No fixed international closing date published; direct applications assessed year-round for February (S1), July (S2) intakes | S31: A$58,540 per 48 credit points | T31: Monash states 'over 360 types of scholarships' and International Study Grants 'valued at up to $10,000' (course pages); named-scholarship details not verified this pass | U31: Student visa (subclass 500) - 'If you are an international student, you will need a student visa (subclass 500) to study at Monash' | V31: Apply directly to Monash online (A$125 applicant fee, or a waiver code); VTAC only if completing Australian Year 12 anywhere or IB in Australia/NZ | W31: Actual course: Bachelor of Laws (Honours), code L3001. CRICOS 080585G. Intakes Feb (S1), Jul (S2). Clayton | X31: Confirmed | Y31: Sheet URL dead/wrong code; sheet duration 5 wrong (4.25); sheet IB 38-42 wrong (36); sheet CBSE 93%/ISC 88% wrong (85%/80%); sheet tuition 54,000-62,000 vs actual 58,540 | Z31: https://www.monash.edu/study/courses/find-a-course/laws-l3001?international=true | AA31: 2027 entry scores: ATAR 95; GCE A Level 13; IB 36; AISSCE (CBSE) 85%; ISC 80%. English Level C: '7.0 overall score for IELTS (Academic), with minimum band scores ... 6.5'. 'The fees for 2027 are: A$58,540'. CRICOS code: 080585G | AB31: 13 September 2026 | AD31: Pave verification, web-checked | AE31: Certified transcripts, passport copy, evidence of English, translations where needed, A$125 applicant fee (per monash.edu/admissions/apply/online) | AF31: 2027 requirements shown; no fixed close date published | AG31: 2027 | AH31: A$125 | AJ31: 85% - Monash India method: 'Overall average of the best four academic subjects' on the official CBSE Marks Statement / ISC Statement of Marks | ISC: 80% - Monash India method: 'Overall average of the best four academic subjects' on the official CBSE Marks Statement / ISC Statement of Marks
A32: AU-031 | B32: University of Queensland (UQ) | C32: Australia | D32: Bachelor of Commerce | E32: Bachelor | F32: https://study.uq.edu.au/study-options/programs/bachelor-commerce-2336 | G32: Go8 / Top Research | H32: English | I32: 3 | K32: 32 (international, S1 2027; domestic guide shows ATAR 82 / IB 31) | L32: 10 - aggregate of best 3 A Levels (A*=6, A=5, B=4, C=3, D=2, E=1; AS = half) | M32: 70% - UQ India method: 'All India Senior School Certificate Examination (CBSE) and Indian Certificate of Secondary Education (ICSE) - grade average of 4 best subjects converted to a percentage' | N32: Not listed separately - UQ groups CBSE and ICSE at the same score (70%); India State Boards (6 approved boards) 85% | O32: Prerequisites: General English subject (Units 3&4, C) and Mathematical Methods (Units 3&4, C) - IB: Maths AA(SL/HL) or AI(SL/HL); CBSE: Mathematics/Applied Mathematics. No admissions test | P32: IELTS Academic 6.5 overall; R6.0 W6.0 S6.0 L6.0 (program page); TOEFL iBT 87 (L19 R19 W21 S19); PTE 64 | Q32: None published for this course | R32: S1 (Feb) commencement: close 30 November of the previous year; S2 (Jul) commencement: close 31 May of the year of commencement | S32: AUD 56,800 per year | T32: Program pages state 'Scholarships available'; named international UG scholarships not verified this pass | U32: Student visa (subclass 500) after acceptance | V32: Direct online via UQ applications portal (apply.uq.edu.au) or a UQ-approved agent; QTAC if studying Australian Year 12 or IB in Australia | W32: CRICOS 001944K. Intakes: Semester 1 (22 Feb 2027) and Semester 2 (26 Jul 2027) | X32: Confirmed | Y32: Sheet CBSE 83% wrong (70%); sheet ISC 76% not published (grouped with CBSE at 70%); sheet tuition 54,096 is not the 2027 figure (56,800) | Z32: https://study.uq.edu.au/study-options/programs/bachelor-commerce-2336 (entry-requirements selector, S1 2027, India) | AA32: Minimum entry score S1 2027: IB Diploma 32; GCE A and AS Levels 10; 'All India Senior School Certificate Examination (CBSE) and Indian Certificate of Secondary Education (ICSE)' 70; fee 'AUD $56,800' for 2027; CRICOS 001944K | AB32: 13 September 2026 | AC32: yes | AD32: Pave verification, web-checked | AE32: Transcripts, English test evidence, passport - via apply.uq.edu.au | AF32: For S1 (22 Feb 2027) start; S2 2027 closes 2027-05-31 | AG32: 2027 | AH32: Application fee not clearly published on official pages checked 13 Sep 2026 (UQ's non-award page cites A$150/application; older UG paper form cited A$100) | AI32: 2026-11-30 | AJ32: 70% - UQ India method: 'All India Senior School Certificate Examination (CBSE) and Indian Certificate of Secondary Education (ICSE) - grade average of 4 best subjects converted to a percentage' | ISC: Not listed separately - UQ groups CBSE and ICSE at the same score (70%); India State Boards (6 approved boards) 85%
A33: AU-032 | B33: University of Queensland (UQ) | C33: Australia | D33: Bachelor of Business Management | E33: Bachelor | F33: https://study.uq.edu.au/study-options/programs/bachelor-business-management-2171 | G33: Go8 / Top Research | H33: English | I33: 3 | K33: 27.75 (international, S1 2027) | L33: 5.5 - aggregate of best 3 (or 2) A Levels | M33: 70% - UQ India method: 'All India Senior School Certificate Examination (CBSE) and Indian Certificate of Secondary Education (ICSE) - grade average of 4 best subjects converted to a percentage' | N33: Not listed separately - grouped with CBSE at 70%; India State Boards 75% | O33: Prerequisites: General English (Units 3&4, C) and one of General Maths / Maths Methods / Specialist Maths (Units 3&4, C). No admissions test | P33: IELTS Academic 6.5 overall; R6.0 W6.0 S6.0 L6.0 (program page); TOEFL iBT 87 (L19 R19 W21 S19); PTE 64 | Q33: None published for this course | R33: S1 (Feb) commencement: close 30 November of the previous year; S2 (Jul) commencement: close 31 May of the year of commencement | S33: AUD 56,800 per year | T33: Program pages state 'Scholarships available'; named international UG scholarships not verified this pass | U33: Student visa (subclass 500) after acceptance | V33: Direct online via UQ applications portal (apply.uq.edu.au) or a UQ-approved agent; QTAC if studying Australian Year 12 or IB in Australia | W33: CRICOS 019886A. Intakes S1 (22 Feb 2027), S2 (26 Jul 2027). St Lucia | X33: Confirmed | Y33: Sheet URL dead (2338); sheet IB 30-34 wrong (27.75); sheet CBSE 80%/ISC 73% wrong (70% grouped); sheet tuition 54,096 not the 2027 figure (56,800) | Z33: https://study.uq.edu.au/study-options/programs/bachelor-business-management-2171 (entry-requirements selector, S1 2027, India) | AA33: Minimum entry score S1 2027: IB 27.75; GCE A/AS Levels 5.5; CBSE/ICSE 70; India State Boards 75. FEES box: 'A$56800'; CRICOS CODE 019886A; QTAC CODE 709001 | AB33: 13 September 2026 | AD33: Pave verification, web-checked | AE33: Transcripts, English test evidence, passport - via apply.uq.edu.au | AF33: For S1 (22 Feb 2027) start; S2 2027 closes 2027-05-31 | AG33: 2027 | AH33: Application fee not clearly published on official pages checked 13 Sep 2026 (UQ's non-award page cites A$150/application; older UG paper form cited A$100) | AI33: 2026-11-30 | AJ33: 70% - UQ India method: 'All India Senior School Certificate Examination (CBSE) and Indian Certificate of Secondary Education (ICSE) - grade average of 4 best subjects converted to a percentage' | ISC: Not listed separately - grouped with CBSE at 70%; India State Boards 75%
A34: AU-033 | B34: University of Queensland (UQ) | C34: Australia | D34: Bachelor of Engineering (Honours) | E34: Bachelor | F34: https://study.uq.edu.au/study-options/programs/bachelor-engineering-honours-2455 | G34: Go8 / Top Research | H34: English | I34: 4 | K34: 32.75 (international, S1 2027) | L34: 10.5 - aggregate of best 3 A Levels; prerequisites A/AS Maths plus A/AS Physics or Chemistry | M34: 70% - UQ India method: 'All India Senior School Certificate Examination (CBSE) and Indian Certificate of Secondary Education (ICSE) - grade average of 4 best subjects converted to a percentage'; prerequisites: English, Mathematics, plus Physics/Chemistry | N34: Not listed separately - grouped with CBSE at 70%; India State Boards 85% | O34: Prerequisites: General English (Units 3&4, C); Mathematical Methods (Units 3&4, C); one of Chemistry or Physics (Units 3&4, C). IB: Maths (AA any / AI SL-HL per list) + Physics or Chemistry (HL/SL). No admissions test | P34: IELTS Academic 6.5 overall; R6.0 W6.0 S6.0 L6.0 (program page); TOEFL iBT 87 (L19 R19 W21 S19); PTE 64 | Q34: None published for this course | R34: S1 (Feb) commencement: close 30 November of the previous year; S2 (Jul) commencement: close 31 May of the year of commencement | S34: AUD 60,952 per year | T34: Program pages state 'Scholarships available'; named international UG scholarships not verified this pass | U34: Student visa (subclass 500) after acceptance | V34: Direct online via UQ applications portal (apply.uq.edu.au) or a UQ-approved agent; QTAC if studying Australian Year 12 or IB in Australia | W34: CRICOS 080734K. AQF Level 8. Intakes S1 (22 Feb 2027), S2 (26 Jul 2027) | X34: Confirmed | Y34: Sheet URL dead (2280); sheet IB 36-40 wrong (32.75); sheet A-level AAB wrong (10.5 aggregate); sheet CBSE 90%/ISC 85% wrong (70% grouped); sheet tuition 55,000-62,000 - actual 60,952 (2027) | Z34: https://study.uq.edu.au/study-options/programs/bachelor-engineering-honours-2455 (entry-requirements selector, S1 2027, India) | AA34: Minimum entry score S1 2027: IB 32.75; GCE A/AS Levels 10.5; CBSE/ICSE 70 (prereqs 'Chemistry', 'Physics', 'Mathematics, Applied Mathematics from CBSE'); FEES 'A$60952'; CRICOS CODE 080734K | AB34: 13 September 2026 | AD34: Pave verification, web-checked | AE34: Transcripts, English test evidence, passport - via apply.uq.edu.au | AF34: For S1 (22 Feb 2027) start; S2 2027 closes 2027-05-31 | AG34: 2027 | AH34: Application fee not clearly published on official pages checked 13 Sep 2026 (UQ's non-award page cites A$150/application; older UG paper form cited A$100) | AI34: 2026-11-30 | AJ34: 70% - UQ India method: 'All India Senior School Certificate Examination (CBSE) and Indian Certificate of Secondary Education (ICSE) - grade average of 4 best subjects converted to a percentage'; prerequisites: English, Mathematics, plus Physics/Chemistry | ISC: Not listed separately - grouped with CBSE at 70%; India State Boards 85%
A35: AU-034 | B35: University of Queensland (UQ) | C35: Australia | D35: Bachelor of Science | E35: Bachelor | F35: https://study.uq.edu.au/study-options/programs/bachelor-science-2461 | G35: Go8 / Top Research | H35: English | I35: 3 | K35: 30.25 (international, S1 2027) | L35: 8.5 - aggregate of best 3 A Levels | M35: 70% - UQ India method: 'All India Senior School Certificate Examination (CBSE) and Indian Certificate of Secondary Education (ICSE) - grade average of 4 best subjects converted to a percentage' | N35: Not listed separately - grouped with CBSE at 70%; India State Boards 80% | O35: Prerequisites: General English (Units 3&4, C); Mathematical Methods (Units 3&4, C); one of Biology, Chemistry, Earth & Environmental Science or Physics (Units 3&4, C). No admissions test | P35: IELTS Academic 6.5 overall; R6.0 W6.0 S6.0 L6.0 (program page); TOEFL iBT 87 (L19 R19 W21 S19); PTE 64 | Q35: None published for this course | R35: S1 (Feb) commencement: close 30 November of the previous year; S2 (Jul) commencement: close 31 May of the year of commencement | S35: AUD 56,800 per year | T35: Program pages state 'Scholarships available'; named international UG scholarships not verified this pass | U35: Student visa (subclass 500) after acceptance | V35: Direct online via UQ applications portal (apply.uq.edu.au) or a UQ-approved agent; QTAC if studying Australian Year 12 or IB in Australia | W35: CRICOS 001961J. Intakes S1 (22 Feb 2027), S2 (26 Jul 2027) | X35: Confirmed | Y35: Sheet URL dead (2045); sheet CBSE 80%/ISC 73% wrong (70% grouped); sheet tuition 52,000-58,000 - published 2027 fee 56,800 | Z35: https://study.uq.edu.au/study-options/programs/bachelor-science-2461 (entry-requirements selector, S1 2027, India) | AA35: Minimum entry score S1 2027: IB 30.25; GCE A/AS Levels 8.5; CBSE/ICSE 70; India State Boards 80. FEES 'A$56800'; CRICOS CODE 001961J | AB35: 13 September 2026 | AD35: Pave verification, web-checked | AE35: Transcripts, English test evidence, passport - via apply.uq.edu.au | AF35: For S1 (22 Feb 2027) start; S2 2027 closes 2027-05-31 | AG35: 2027 | AH35: Application fee not clearly published on official pages checked 13 Sep 2026 (UQ's non-award page cites A$150/application; older UG paper form cited A$100) | AI35: 2026-11-30 | AJ35: 70% - UQ India method: 'All India Senior School Certificate Examination (CBSE) and Indian Certificate of Secondary Education (ICSE) - grade average of 4 best subjects converted to a percentage' | ISC: Not listed separately - grouped with CBSE at 70%; India State Boards 80%
A36: AU-035 | B36: University of Queensland (UQ) | C36: Australia | D36: Bachelor of Laws (Honours) | E36: Bachelor | F36: https://study.uq.edu.au/study-options/programs/bachelor-laws-honours-2471 | G36: Go8 / Top Research | H36: English | I36: 4 | K36: 41.75 (international, S1 2027) | L36: 15 - aggregate of best 3 A Levels | M36: 97% - UQ India method: 'All India Senior School Certificate Examination (CBSE) and Indian Certificate of Secondary Education (ICSE) - grade average of 4 best subjects converted to a percentage' | N36: Not listed separately - grouped with CBSE at 97% | O36: No LNAT/admissions test or interview published; selection on entry scores. Honours awarded on GPA within the standard program | P36: IELTS 7.0 overall; writing 7, speaking 7, reading 6, listening 6; TOEFL iBT 100 (W27 S23 L19 R19); PTE 72 - higher than UQ standard | Q36: None published for this course | R36: Semester 1 only: applications close 30 November of the previous year | S36: AUD 56,800 per year | T36: Program pages state 'Scholarships available'; named international UG scholarships not verified this pass | U36: Student visa (subclass 500) after acceptance | V36: Direct online via UQ applications portal (apply.uq.edu.au) or a UQ-approved agent; QTAC if studying Australian Year 12 or IB in Australia | W36: CRICOS 082613C. AQF Level 8. Start: Semester 1 (22 Feb 2027) only | X36: Confirmed | Y36: Sheet URL dead (2440); sheet IB 38-42 low end wrong (41.75); sheet CBSE 93%/ISC 88% wrong (97% grouped); sheet said IELTS sub-bands 6.5 - actual is W7 S7 R6 L6; sheet missed that there is no July intake | Z36: https://study.uq.edu.au/study-options/programs/bachelor-laws-honours-2471 (entry-requirements selector, S1 2027, India) | AA36: Minimum entry score S1 2027: IB 41.75; GCE A/AS Levels 15; CBSE/ICSE 97. 'IELTS overall 7; writing 7; speaking 7; reading 6; listening 6.' FEES 'A$56800'; CRICOS CODE 082613C | AB36: 13 September 2026 | AD36: Pave verification, web-checked | AE36: Transcripts, English test evidence, passport - via apply.uq.edu.au | AF36: For S1 (22 Feb 2027) start; NO Semester 2 intake | AG36: 2027 | AH36: Application fee not clearly published on official pages checked 13 Sep 2026 (UQ's non-award page cites A$150/application; older UG paper form cited A$100) | AI36: 2026-11-30 | AJ36: 97% - UQ India method: 'All India Senior School Certificate Examination (CBSE) and Indian Certificate of Secondary Education (ICSE) - grade average of 4 best subjects converted to a percentage' | ISC: Not listed separately - grouped with CBSE at 97%
A37: AU-036 | B37: University of Queensland (UQ) | C37: Australia | D37: Bachelor of Advanced Finance and Economics (Honours) | E37: Bachelor | F37: https://study.uq.edu.au/study-options/programs/bachelor-advanced-finance-and-economics-honours-2140 | G37: Go8 / Top Research | H37: English | I37: 4 | K37: 43.25 (international, S1 2027) | L37: 15 - aggregate of best 3 A Levels; prerequisite includes A Level Mathematics/Pure Mathematics | M37: 97% - UQ India method: 'All India Senior School Certificate Examination (CBSE) and Indian Certificate of Secondary Education (ICSE) - grade average of 4 best subjects converted to a percentage'; prerequisites Mathematics/Applied Mathematics | N37: Not listed separately - grouped with CBSE at 97% | O37: Very high cutoffs (IB 43.25); Specialist-Maths-level prerequisite (IB Maths AA HL / Further Maths HL; A Level Maths); no interview/test published | P37: IELTS Academic 6.5 overall; R6.0 W6.0 S6.0 L6.0 (program page); TOEFL iBT 87 (L19 R19 W21 S19); PTE 64 | Q37: None published for this course | R37: Semester 1 only: applications close 30 November of the previous year | S37: AUD 60,952 per year | T37: Program pages state 'Scholarships available'; named international UG scholarships not verified this pass | U37: Student visa (subclass 500) after acceptance | V37: Direct online via UQ applications portal (apply.uq.edu.au) or a UQ-approved agent; QTAC if studying Australian Year 12 or IB in Australia | W37: CRICOS 088354B. AQF Level 8. Start: Semester 1 (22 Feb 2027) only. Embedded honours with research thesis | X37: Confirmed | Y37: Sheet URL dead (2498); sheet IB 37-41 wrong (43.25); sheet A-level AAA wrong (15 aggregate); sheet CBSE 93%/ISC 88% wrong (97% grouped); sheet tuition 55,000-62,000 - actual 60,952; sheet missed S1-only intake | Z37: https://study.uq.edu.au/study-options/programs/bachelor-advanced-finance-and-economics-honours-2140 (entry-requirements selector, S1 2027, India) | AA37: Minimum entry score S1 2027: IB 43.25; GCE A/AS Levels 15; CBSE/ICSE 97 (prereq 'Mathematics, Applied Mathematics from CBSE'). FEES 'A$60952'; CRICOS CODE 088354B | AB37: 13 September 2026 | AD37: Pave verification, web-checked | AE37: Transcripts, English test evidence, passport - via apply.uq.edu.au | AF37: For S1 (22 Feb 2027) start; NO Semester 2 intake | AG37: 2027 | AH37: Application fee not clearly published on official pages checked 13 Sep 2026 (UQ's non-award page cites A$150/application; older UG paper form cited A$100) | AI37: 2026-11-30 | AJ37: 97% - UQ India method: 'All India Senior School Certificate Examination (CBSE) and Indian Certificate of Secondary Education (ICSE) - grade average of 4 best subjects converted to a percentage'; prerequisites Mathematics/Applied Mathematics | ISC: Not listed separately - grouped with CBSE at 97%
A38: AU-037 | B38: Adelaide University (merged University of Adelaide + UniSA; sheet listed University of Adelaide) | C38: Australia | D38: Bachelor of Commerce | E38: Bachelor | F38: https://adelaide.edu.au/study/degrees/bachelor-of-commerce-accounting/ | G38: Go8 / Top Research | H38: English | I38: 3 | J38: ATAR 80 (Australian benchmark). Prerequisites: None | K38: 28 (Bachelor of Commerce majoring in Accounting, international admissions criteria, 2026 entry) | L38: Not published as letter grades; Adelaide University lists GCE A Level points on the degree page rather than a grade string — sheet's 'BBB' not verifiable | M38: CBSE: 75 (published under 'CBSE and CISCE' on the international admissions criteria; State Board Examinations: 85) | N38: CISCE: 75 (same published 'CBSE and CISCE' figure) | O38: Rank-based: where there are more eligible applicants than places, admission is competitive on the entry criteria; CRICOS 115684M (Accounting major) | P38: IELTS Overall 6.5, minimum 6.0 in Reading, Listening, Speaking, Writing (Adelaide University standard for this degree); alternatives accepted | Q38: None | R38: Intakes February (Semester 1) and July (Semester 2); no fixed university-wide closing date published — 'Some degrees have different deadlines, so we recommend reviewing the degree page to be sure.' | S38: AUD 54,300 per year (indicative international annual fee) | T38: Adelaide University offers a range of international scholarships with automatic assessment on application ('For most scholarships, you will be automatically assessed when applying'); the sheet's 'Adelaide International Undergraduate Scholarships / Bonython Scholarship' are legacy University of Adelaide names not found on the new site | U38: Australian Student visa (subclass 500) applied for after accepting the offer and receiving the CoE — Adelaide University's how-to-apply steps end with 'receive CoE' then 'Apply for student visa' | V38: Adelaide University International Application System (StudyLink, student-adelaideuni.studylink.com) or an official Education Agent | W38: MERGER: Adelaide University is the new institution formed by the merger of the University of Adelaide and the University of South Australia, officially open since January 2026 with its first cohort starting February 2026 — a 2027 applicant applies to ADELAIDE UNIVERSITY. Old URL https://www.adelaide.edu.au/degree-finder/bcom.html now redirects to the generic adelaide.edu.au/study/ landing page (course value lost). The plain Bachelor of Commerce page 404s: the degree is now published per major (Accounting, Banking and Finance, Business Analytics, etc.); figures here are from the Accounting major page. CRICOS in notes: 115684M. | X38: Confirmed | Y38: Sheet said IB 30-33 — published IB is 28. Sheet CBSE 80%+/ISC 73%+ — published CBSE/CISCE figure is 75 (State Boards 85). Sheet tuition AUD 43,000-48,000 — 2026 international fee is AUD 54,300. Sheet deadline 'May 1' — no such published deadline. Sheet institution 'University of Adelaide' — now Adelaide University. | Z38: https://adelaide.edu.au/study/degrees/bachelor-of-commerce-accounting/ | AA38: "IB Diploma Entry Score: 28 points ... CBSE and CISCE: 75 ... Annual Tuition Fee: AUD $54,300 (indicative)" (degree page admissions criteria for international students); merger: "The new Adelaide University has officially opened its doors, completing the merger process between the former University of Adelaide and University of South Australia." (statedevelopment.sa.gov.au) | AB38: 13 September 2026 | AC38: yes | AD38: Pave verification, web-checked | AE38: Academic certificates and transcripts, proof of English language proficiency, proof of identity (passport); non-English documents must be officially translated | AF38: Checked 13 September 2026: Adelaide University publishes no fixed international closing dates for 2027 intakes; apply well ahead of the February/July start | AG38: 2026 | AH38: AUD 150 non-refundable per application (waived for research degrees, 100% online and non-award programs) | AJ38: CBSE: 75 (published under 'CBSE and CISCE' on the international admissions criteria; State Board Examinations: 85) | ISC: CISCE: 75 (same published 'CBSE and CISCE' figure)
A39: AU-038 | B39: Adelaide University (merged University of Adelaide + UniSA; sheet listed University of Adelaide) | C39: Australia | D39: Bachelor of Engineering (Honours) | E39: Bachelor (Honours) | F39: https://adelaide.edu.au/study/degrees/bachelor-of-engineering-mechanical-honours/ | G39: Go8 / Top Research | H39: English | I39: 4 | J39: ATAR 80 (Australian benchmark). Prerequisite: SACE Stage 2 Mathematical Methods (or equivalent). Assumed knowledge: None | K39: 28 (Bachelor of Engineering (Mechanical) (Honours), international admissions criteria, 2026 entry; other disciplines have their own pages) | L39: Not published as letter grades on the new degree pages — sheet's 'ABB (Maths/Sci)' not verifiable | M39: CBSE: 75 (published under 'CBSE and CISCE'; State Board Examinations: 85) | N39: CISCE: 75 | O39: Rank-based competitive selection where applicants exceed places; provisionally accredited by Engineers Australia; CRICOS 115703B (Mechanical) | P39: IELTS Overall 6.5, minimum 6.0 in each of Reading, Listening, Speaking, Writing | Q39: None | R39: Intakes February and July; no fixed university-wide closing date published — 'Some degrees have different deadlines, so we recommend reviewing the degree page to be sure.' | S39: AUD 57,100 per year (indicative international annual fee, Mechanical) | T39: Range of Adelaide University international scholarships, automatically assessed on application; legacy University of Adelaide scholarship names in the sheet no longer verifiable | U39: Australian Student visa (subclass 500) after acceptance and CoE (per Adelaide University how-to-apply steps) | V39: Adelaide University International Application System (StudyLink, student-adelaideuni.studylink.com) or an official Education Agent | W39: MERGER: applies to ADELAIDE UNIVERSITY (merger of University of Adelaide and UniSA, open January 2026, first cohort February 2026). Old URL https://www.adelaide.edu.au/degree-finder/benghons.html redirects to the generic study landing page. There is no single generic BEng(Hons) programme any more: Adelaide University publishes separate degrees per discipline (Civil, Chemical, Electrical, Mechanical, Environmental, Software, etc.); figures here are from the Mechanical page — check the specific discipline page. Physics is NOT a stated prerequisite for Mechanical (only Mathematical Methods; assumed knowledge 'None'). CRICOS in notes: 115703B (Mechanical). | X39: Confirmed | Y39: Sheet said IB 34-38 — published IB is 28. Sheet ATAR 90+ — published ATAR 80. Sheet 'Maths/Physics required' — only Mathematical Methods is a prerequisite (Mechanical). Sheet tuition AUD 46,000-54,000 — 2026 fee is AUD 57,100. Sheet CBSE 88%+/ISC 82%+ — published CBSE/CISCE figure is 75. Sheet deadline 'May 1' — not published. | Z39: https://adelaide.edu.au/study/degrees/bachelor-of-engineering-mechanical-honours/ | AA39: "Annual Tuition Fee: $57,100 AUD per year (2026) ... IB Diploma Entry Score: 28 ... Subject Prerequisites: SACE Stage 2 Mathematical Methods (or equivalent)" (international admissions criteria on the degree page) | AB39: 13 September 2026 | AC39: yes | AD39: Pave verification, web-checked | AE39: Academic certificates and transcripts, proof of English proficiency, passport; official translations if not in English | AF39: Checked 13 September 2026: no published international closing dates for 2027 intakes | AG39: 2026 | AH39: AUD 150 non-refundable per application | AJ39: CBSE: 75 (published under 'CBSE and CISCE'; State Board Examinations: 85) | ISC: CISCE: 75
A40: AU-039 | B40: Adelaide University (merged University of Adelaide + UniSA; sheet listed University of Adelaide) | C40: Australia | D40: Bachelor of Computer Science | E40: Bachelor | F40: https://adelaide.edu.au/study/degrees/bachelor-of-computer-science/ | G40: Go8 / Top Research | H40: English | I40: 3 | J40: ATAR 75 (Australian benchmark). Prerequisites: none stated | K40: 26 (international admissions criteria, 2026 entry) | L40: GCE Advanced Levels: 8 (points as published on the degree page; not a letter-grade string) | M40: CBSE: 70 (published under 'CBSE and CISCE'; State Board Examinations: 80) | N40: CISCE: 70 | O40: "In cases where there are more eligible applicants than available places, admission will be competitive with ranks based on the entry criteria." CRICOS 115685K | P40: IELTS Overall 6.5 with Reading 6, Listening 6, Speaking 6, Writing 6 | Q40: None | R40: Intakes February and July; no fixed university-wide closing date published — 'Some degrees have different deadlines, so we recommend reviewing the degree page to be sure.' | S40: AUD 55,400 per year (indicative international annual fee) | T40: Range of Adelaide University international scholarships, automatically assessed on application | U40: Australian Student visa (subclass 500) after acceptance and CoE (per Adelaide University how-to-apply steps) | V40: Adelaide University International Application System (StudyLink) or an official Education Agent | W40: MERGER: applies to ADELAIDE UNIVERSITY (merger of University of Adelaide and UniSA, open January 2026). Old URL https://www.adelaide.edu.au/degree-finder/bcompsci.html redirects to the generic study landing page. Also offered with named majors (AI & ML, Human-Centred Computing, Programming Languages) and as an Honours variant, each with its own page. CRICOS in notes: 115685K. | X40: Confirmed | Y40: Sheet said IB 30-33 — published IB is 26. Sheet ATAR 80+ — published ATAR 75. Sheet CBSE 80%+/ISC 73%+ — published CBSE/CISCE figure is 70 (State Boards 80). Sheet tuition AUD 44,000-50,000 — 2026 fee is AUD 55,400. Sheet deadline 'May 1' — not published. | Z40: https://adelaide.edu.au/study/degrees/bachelor-of-computer-science/ | AA40: "International Baccalaureate: 26 ... CBSE and CISCE: 70 ... $55,400 (indicative annual fees for full-time study) ... a non-refundable application fee of AUD$150 applies for every application submitted" | AB40: 13 September 2026 | AC40: yes | AD40: Pave verification, web-checked | AE40: Academic certificates and transcripts, proof of English proficiency, passport; official translations if not in English | AF40: Checked 13 September 2026: no published international closing dates for 2027 intakes | AG40: 2026 | AH40: AUD 150 non-refundable per application | AJ40: CBSE: 70 (published under 'CBSE and CISCE'; State Board Examinations: 80) | ISC: CISCE: 70
A41: AU-040 | B41: Adelaide University (merged University of Adelaide + UniSA; sheet listed University of Adelaide) | C41: Australia | D41: Bachelor of Laws (LLB) | E41: Bachelor (Honours) — now titled Bachelor of Laws (Honours) | F41: https://adelaide.edu.au/study/degrees/bachelor-of-laws-honours/ | G41: Go8 / Top Research | H41: English | I41: 4 | J41: ATAR 85 (Australian benchmark). Prerequisites: None | K41: 30 (international admissions criteria, 2026 entry) | L41: Not published as letter grades on the new degree page — sheet's 'AAA' not verifiable | M41: CBSE: 80 (published under 'CBSE and CISCE'; State Board Examinations: 90) | N41: CISCE: 80 | O41: Rank-based competitive selection; qualifying degree for admission to legal practice; also offered as double degrees with Commerce, Arts, Business, International Relations; CRICOS 115725G | P41: IELTS Overall 7.0 with 7.0 in each of Reading, Listening, Speaking, Writing (higher than the university standard) | Q41: None (no LNAT/interview published) | R41: Intakes February and July; no fixed university-wide closing date published — 'Some degrees have different deadlines, so we recommend reviewing the degree page to be sure.' | S41: AUD 57,100 per year (indicative international annual fee, 2026 intake; 'Fees are subject to change annually.') | T41: Range of Adelaide University international scholarships, automatically assessed on application | U41: Australian Student visa (subclass 500) after acceptance and CoE (per Adelaide University how-to-apply steps) | V41: Adelaide University International Application System (StudyLink, student-adelaideuni.studylink.com) or an official Education Agent | W41: MERGER: applies to ADELAIDE UNIVERSITY (merger of University of Adelaide and UniSA, open January 2026, first cohort February 2026). The degree is now the Bachelor of Laws (Honours), 4 years. Old URL https://www.adelaide.edu.au/degree-finder/llb.html redirects to the generic study landing page. CRICOS in notes: 115725G. | X41: Confirmed | Y41: Sheet said IB 38-42 — published IB is 30 (largest gap in this set). Sheet ATAR 97+ — published ATAR 85. Sheet CBSE 93%+/ISC 88%+ — published CBSE/CISCE figure is 80 (State Boards 90). Sheet IELTS 7.0 no band <6.5 — published requirement is 7.0 in every band. Sheet tuition AUD 44,000-50,000 — 2026 fee is AUD 57,100. Sheet deadline 'May 1' — not published. | Z41: https://adelaide.edu.au/study/degrees/bachelor-of-laws-honours/ | AA41: "IB Diploma Entry Score: 30 points ... CBSE and CISCE require 80 ... $57,100 for indicative annual fees (2026 intake); Fees are subject to change annually. ... IELTS Overall 7 with component scores of 7" | AB41: 13 September 2026 | AC41: yes | AD41: Pave verification, web-checked | AE41: Academic certificates and transcripts, proof of English proficiency, passport; official translations if not in English | AF41: Checked 13 September 2026: no published international closing dates for 2027 intakes | AG41: 2026 | AH41: AUD 150 non-refundable per application | AJ41: CBSE: 80 (published under 'CBSE and CISCE'; State Board Examinations: 90) | ISC: CISCE: 80
A42: AU-041 | B42: Adelaide University (merged University of Adelaide + UniSA; sheet listed University of Adelaide) | C42: Australia | D42: Bachelor of Science | E42: Bachelor | F42: https://adelaide.edu.au/study/degrees/bachelor-of-science/ | G42: Go8 / Top Research | H42: English | I42: 3 | J42: ATAR 70 (Australian benchmark). Prerequisites: None | K42: 25 (international admissions criteria, 2026 entry) | L42: Not captured as letter grades on the new degree page — sheet's 'BCC' not verifiable | M42: CBSE: 65 (published under 'CBSE and CISCE'; State Board Examinations: 75) | N42: CISCE: 65 | O42: Rank-based competitive selection where applicants exceed places; program code BSCIE; CRICOS 115751E | P42: IELTS Overall 6.5, minimum 6.0 in each of Reading, Listening, Speaking, Writing; alternatives accepted | Q42: None | R42: Intakes February and July; no fixed university-wide closing date published — 'Some degrees have different deadlines, so we recommend reviewing the degree page to be sure.' | S42: AUD 55,400 per year (indicative international annual fee) | T42: Range of Adelaide University international scholarships, automatically assessed on application | U42: Australian Student visa (subclass 500) after acceptance and CoE (per Adelaide University how-to-apply steps) | V42: Adelaide University International Application System (StudyLink) or an official Education Agent | W42: MERGER: applies to ADELAIDE UNIVERSITY (merger of University of Adelaide and UniSA, open January 2026). Old URL https://www.adelaide.edu.au/degree-finder/bsc.html redirects to the generic study landing page. CRICOS in notes: 115751E. | X42: Confirmed | Y42: Sheet said IB 27-31 — published IB is 25. Sheet CBSE 77%+/ISC 70%+ — published CBSE/CISCE figure is 65 (State Boards 75). Sheet tuition AUD 43,000-48,000 — 2026 fee is AUD 55,400. Sheet deadline 'May 1' — not published. | Z42: https://adelaide.edu.au/study/degrees/bachelor-of-science/ | AA42: "IB Diploma Entry Score: 25 points ... CBSE and CISCE: 65% ... Annual Tuition Fee: AUD $55,400 (indicative, subject to annual change)" | AB42: 13 September 2026 | AC42: yes | AD42: Pave verification, web-checked | AE42: Academic certificates and transcripts, proof of English proficiency, passport; official translations if not in English | AF42: Checked 13 September 2026: no published international closing dates for 2027 intakes | AG42: 2026 | AH42: AUD 150 non-refundable per application | AJ42: CBSE: 65 (published under 'CBSE and CISCE'; State Board Examinations: 75) | ISC: CISCE: 65
A43: AU-042 | B43: University of Western Australia (UWA) | C43: Australia | D43: Bachelor of Commerce | E43: Bachelor | F43: https://www.uwa.edu.au/study/courses/bachelor-of-commerce | G43: Go8 / Top Research | H43: English | I43: 3 | J43: Minimum ATAR 80; must satisfy any prerequisites for the preferred major | K43: 27 (via UWA's published IB-to-ATAR conversion: course minimum ATAR 80 = IB 27; UWA sets no absolute IB minimum, students 'must meet equivalent entry standards to other applicants') | L43: No letter-grade requirement published; UWA ranks A levels to a selection rank against ATAR 80 | M43: CBSE AISSCE: 12.0 points on best 4 subjects (A1=5, A2=4.5, B1=3.5, B2=3 ...) = ATAR 80 equivalent; Class XII English Language B2 or higher can satisfy English competence | N43: CISCE ISC: average of best four subjects 70 = ATAR 80 equivalent; English Core 60% or higher can satisfy English competence | O43: Rank-based on ATAR-equivalent selection rank; no interviews or tests; CRICOS 003006C | P43: IELTS Academic minimum overall 6.5 with no band less than 6.0; TOEFL iBT minimum 82 with 20 in Speaking and Writing (university-wide undergraduate standard); CBSE/ISC English as above | Q43: None | R43: Intakes February and July. Published 2026 closing dates: Semester 1 by 19 January 2026 and Semester 2 by 8 June 2026 for 'most other countries' (some countries: 29 December 2025 / 11 May 2026; onshore: 20 February / 17 July 2026) | S43: AUD 50,700 per year (international undergraduate fee, course BP002) | T43: UWA Global Excellence Scholarship: automatic assessment, AUD 6,000-12,000 per year by equivalent ATAR (85-89.95: $6,000; 90-97.95: $10,000; 98+: $12,000), up to AUD 48,000 over four years | U43: Australian Student visa (subclass 500) after acceptance and CoE (standard national process; not separately restated on UWA course pages) | V43: Direct online via the UWA Application Portal, or through a UWA agent | W43: Course page publishes no fee or per-qualification scores directly — fee from UWA's official fee list (fees.uwa.edu.au, INTUG 2026), qualification equivalences from UWA's international qualifications and IB pages. CRICOS in notes: 003006C. | X43: Confirmed | Y43: Sheet said ATAR 75+ / IB 28 — course minimum is ATAR 80, which converts to IB 27 on UWA's own table. Sheet CBSE 78%+/ISC 71%+ — UWA uses best-4 points (CBSE 12.0 points) and best-4 average (ISC 70) for ATAR 80, not those percentages. Sheet tuition AUD 39,000-44,000 — 2026 fee is AUD 50,700. Sheet deadline 'July 17' is the ONSHORE Semester 2 date; offshore internationals close earlier (8 June 2026 for most countries). | Z43: https://www.fees.uwa.edu.au/Browse/BrowseCourses?feeType=INTUG&feeYear=2026 | AA43: "Bachelor of Commerce (BP002): $50,700" (2026 international undergraduate fees list); entry: course page 'Minimum ATAR of 80'; IB conversion table: IB 27 = ATAR 80.00 | AB43: 13 September 2026 | AC43: yes | AD43: Pave verification, web-checked | AE43: Copy of academic results, English test results, passport, plus any course-specific documents; scans clear and in full colour | AF43: Checked 13 September 2026: 2026 windows have passed; Semester 1 2027 closing dates not yet published — 'Dates are subject to change without notice and some courses have different application date requirements.' | AG43: 2026 | AH43: AUD 150 non-refundable ('International students applying directly to UWA and agents applying on behalf of students to study at UWA will need to pay a non-refundable fee of $150.') | AJ43: CBSE AISSCE: 12.0 points on best 4 subjects (A1=5, A2=4.5, B1=3.5, B2=3 ...) = ATAR 80 equivalent; Class XII English Language B2 or higher can satisfy English competence | ISC: CISCE ISC: average of best four subjects 70 = ATAR 80 equivalent; English Core 60% or higher can satisfy English competence
A44: AU-043 | B44: University of Western Australia (UWA) | C44: Australia | D44: Bachelor of Science | E44: Bachelor | F44: https://www.uwa.edu.au/study/courses/bachelor-of-science | G44: Go8 / Top Research | H44: English | I44: 3 | J44: Minimum ATAR 70; must satisfy any prerequisites for the preferred major (varies by major) | K44: 24 (via UWA's published IB-to-ATAR conversion: course minimum ATAR 70 = IB 24; no absolute IB minimum published) | L44: No letter-grade requirement published; A levels ranked to a selection rank against ATAR 70 | M44: CBSE AISSCE: 9.0 points on best 4 subjects = ATAR 70 equivalent; Class XII English Language B2 or higher can satisfy English competence | N44: CISCE ISC: average of best four subjects 60 = ATAR 70 equivalent; English Core 60% or higher can satisfy English competence | O44: Rank-based on ATAR-equivalent selection rank; major prerequisites checked at admission; CRICOS 068914G | P44: IELTS Academic minimum overall 6.5 with no band less than 6.0; TOEFL iBT minimum 82 with 20 in Speaking and Writing (university-wide undergraduate standard) | Q44: None | R44: Intakes February and July. Published 2026 closing dates: Semester 1 by 19 January 2026 and Semester 2 by 8 June 2026 for most countries (some countries earlier; onshore 20 February / 17 July 2026) | S44: AUD 52,000 per year (international undergraduate fee, course BP004) | T44: UWA Global Excellence Scholarship: automatic assessment, AUD 6,000-12,000 per year by equivalent ATAR, up to AUD 48,000 over four years | U44: Australian Student visa (subclass 500) after acceptance and CoE (standard national process) | V44: Direct online via the UWA Application Portal, or through a UWA agent | W44: Fee from UWA's official 2026 international fee list; course page itself defers to the fee calculator. CRICOS in notes: 068914G. | X44: Confirmed | Y44: Sheet said IB 26 — ATAR 70 converts to IB 24 on UWA's own table. Sheet CBSE 75%+/ISC 68%+ — UWA uses CBSE 9.0 best-4 points / ISC best-4 average 60 for ATAR 70. Sheet tuition AUD 40,000-46,000 — 2026 fee is AUD 52,000. Sheet deadline 'July 17' is onshore-only; offshore Semester 2 closed 8 June 2026. | Z44: https://www.fees.uwa.edu.au/Browse/BrowseCourses?feeType=INTUG&feeYear=2026 | AA44: "Bachelor of Science (BP004): $52,000" (2026 international undergraduate fees list); course page: 'Minimum ATAR 70'; IB conversion table: IB 24 = ATAR 70.00 | AB44: 13 September 2026 | AC44: yes | AD44: Pave verification, web-checked | AE44: Copy of academic results, English test results, passport, plus any course-specific documents | AF44: Checked 13 September 2026: Semester 1 2027 closing dates not yet published | AG44: 2026 | AH44: AUD 150 non-refundable (direct or via agent) | AJ44: CBSE AISSCE: 9.0 points on best 4 subjects = ATAR 70 equivalent; Class XII English Language B2 or higher can satisfy English competence | ISC: CISCE ISC: average of best four subjects 60 = ATAR 70 equivalent; English Core 60% or higher can satisfy English competence
A45: AU-044 | B45: University of Western Australia (UWA) | C45: Australia | D45: Bachelor of Engineering (Honours) | E45: Bachelor (Honours) | F45: https://www.uwa.edu.au/study/courses/bachelor-of-engineering-honours | G45: Go8 / Top Research | H45: English | I45: 4 | J45: Minimum ATAR 80 (standard entry). Prerequisites: scaled score of at least 50 in Mathematics Methods ATAR, plus one of Chemistry ATAR, Physics ATAR or Mathematics Specialist ATAR (or IB/board equivalents per UWA's equivalency tables) | K45: 27 (via UWA's published IB-to-ATAR conversion: standard-entry minimum ATAR 80 = IB 27; combined degrees ATAR 88, engineering+philosophy ATAR 98) | L45: No letter-grade requirement published; A levels ranked to a selection rank against ATAR 80 | M45: CBSE AISSCE: 12.0 points on best 4 subjects = ATAR 80 equivalent; prerequisite subjects still required | N45: CISCE ISC: average of best four subjects 70 = ATAR 80 equivalent | O45: Rank-based; 9 specialisations chosen within the degree: Automation and Robotics, Biomedical, Chemical, Civil, Electrical and Electronic, Environmental, Mechanical, Mining, Software; CRICOS 106081B | P45: IELTS Academic minimum overall 6.5 with no band less than 6.0; TOEFL iBT minimum 82 with 20 in Speaking and Writing (university-wide undergraduate standard) | Q45: None | R45: Intakes February and July. Published 2026 closing dates: Semester 1 by 19 January 2026 and Semester 2 by 8 June 2026 for most countries (some countries earlier; onshore 20 February / 17 July 2026) | S45: AUD 53,700 per year (international undergraduate fee, course BH011) | T45: UWA Global Excellence Scholarship: automatic assessment, AUD 6,000-12,000 per year by equivalent ATAR, up to AUD 48,000 over four years | U45: Australian Student visa (subclass 500) after acceptance and CoE (standard national process) | V45: Direct online via the UWA Application Portal, or through a UWA agent | W45: Single umbrella BEng(Hons) with specialisation choice (unlike Adelaide University's per-discipline degrees). Fee from UWA's official 2026 international fee list. CRICOS in notes: 106081B. | X45: Confirmed | Y45: Sheet said ATAR 87+ / IB 32-36 — standard entry is ATAR 80, converting to IB 27. Sheet 'Maths required' understates it: Maths Methods PLUS one of Chemistry/Physics/Specialist Maths. Sheet CBSE 85%+/ISC 78%+ — UWA uses CBSE 12.0 best-4 points / ISC average 70 for ATAR 80. Sheet tuition AUD 44,000-52,000 — 2026 fee is AUD 53,700. Sheet deadline 'July 17' is onshore-only. | Z45: https://www.fees.uwa.edu.au/Browse/BrowseCourses?feeType=INTUG&feeYear=2026 | AA45: "Bachelor of Engineering (Honours) (BH011): $53,700" (2026 international undergraduate fees list); course page: 'obtain a scaled score of at least 50 in prerequisite: Mathematics Methods ATAR' plus one of 'Chemistry ATAR, Physics ATAR or Mathematics Specialist ATAR'; minimum ATAR 80 standard entry | AB45: 13 September 2026 | AC45: yes | AD45: Pave verification, web-checked | AE45: Copy of academic results, English test results, passport, plus any course-specific documents | AF45: Checked 13 September 2026: Semester 1 2027 closing dates not yet published | AG45: 2026 | AH45: AUD 150 non-refundable (direct or via agent) | AJ45: CBSE AISSCE: 12.0 points on best 4 subjects = ATAR 80 equivalent; prerequisite subjects still required | ISC: CISCE ISC: average of best four subjects 70 = ATAR 80 equivalent
A46: AU-045 | B46: University of Western Australia (UWA) | C46: Australia | D46: Bachelor of Arts | E46: Bachelor | F46: https://www.uwa.edu.au/study/courses/bachelor-of-arts | G46: Go8 / Top Research | H46: English | I46: 3 | J46: Minimum ATAR 70; satisfy any prerequisites for the preferred majors (most Arts majors have none) | K46: 24 (via UWA's published IB-to-ATAR conversion: course minimum ATAR 70 = IB 24) | L46: No letter-grade requirement published; A levels ranked to a selection rank against ATAR 70 | M46: CBSE AISSCE: 9.0 points on best 4 subjects = ATAR 70 equivalent; Class XII English Language B2 or higher can satisfy English competence | N46: CISCE ISC: average of best four subjects 60 = ATAR 70 equivalent; English Core 60% or higher can satisfy English competence | O46: Rank-based on ATAR-equivalent selection rank; includes the Law and Society major used as the undergraduate pathway to UWA's Juris Doctor; CRICOS 003005D | P46: IELTS Academic minimum overall 6.5 with no band less than 6.0; TOEFL iBT minimum 82 with 20 in Speaking and Writing (university-wide undergraduate standard) | Q46: None | R46: Intakes February and July. Published 2026 closing dates: Semester 1 by 19 January 2026 and Semester 2 by 8 June 2026 for most countries (some countries earlier; onshore 20 February / 17 July 2026) | S46: AUD 42,500 per year (international undergraduate fee, course BP001) | T46: UWA Global Excellence Scholarship: automatic assessment, AUD 6,000-12,000 per year by equivalent ATAR, up to AUD 48,000 over four years | U46: Australian Student visa (subclass 500) after acceptance and CoE (standard national process) | V46: Direct online via the UWA Application Portal, or through a UWA agent | W46: Course code BP001. Fee from UWA's official 2026 international fee list. CRICOS in notes: 003005D. | X46: Confirmed | Y46: Sheet said IB 25 — ATAR 70 converts to IB 24 on UWA's own table (minor). Sheet CBSE 72%+/ISC 65%+ — UWA uses CBSE 9.0 best-4 points / ISC average 60. Sheet tuition AUD 36,000-42,000 — 2026 fee is AUD 42,500 (just above the sheet's upper bound). Sheet deadline 'July 17' is onshore-only. | Z46: https://www.fees.uwa.edu.au/Browse/BrowseCourses?feeType=INTUG&feeYear=2026 | AA46: "Bachelor of Arts (BP001): $42,500" (2026 international undergraduate fees list); course page: 'Minimum ATAR: 70'; IB conversion table: IB 24 = ATAR 70.00 | AB46: 13 September 2026 | AC46: yes | AD46: Pave verification, web-checked | AE46: Copy of academic results, English test results, passport, plus any course-specific documents | AF46: Checked 13 September 2026: Semester 1 2027 closing dates not yet published | AG46: 2026 | AH46: AUD 150 non-refundable (direct or via agent) | AJ46: CBSE AISSCE: 9.0 points on best 4 subjects = ATAR 70 equivalent; Class XII English Language B2 or higher can satisfy English competence | ISC: CISCE ISC: average of best four subjects 60 = ATAR 70 equivalent; English Core 60% or higher can satisfy English competence

Sheet Visa steps
A1: # | B1: stage | C1: title | D1: realistic duration | E1: what happens | F1: the trap | G1: source URL | H1: exact quote | I1: date checked | J1: axes
A2: 1 | B2: Eligibility | C2: Confirm the Indian Standard XII board is a recognised qualification and find the university's own conversion | D2: 1-2 weeks of research, no external processing | E2: Australian universities admit Indian students on Standard XII directly - there is no separate equivalence body, no foundation year, and no APS-style pre-check. The University of Sydney lists 'All India Senior School Certificate (CBSE)', 'Indian School Certificate (CISCE)' and 'Indian Higher Secondary Certificate (State board exams)' among the qualifications it accepts for undergraduate admission. What differs is the arithmetic: each university converts Standard XII to an ATAR-equivalent selection rank on its own scale, so the same marksheet produces different ranks at different universities. | F2: Assuming one CBSE percentage works everywhere. Melbourne uses the average of the best four final-year subjects and, for state boards, accepts only Tamil Nadu HSC, Maharashtra HSC and Karnataka PUC as direct entry; Sydney sums five graded subjects on its own A1=4 ... D2=0.5 scale. Quoting a student a single 'cutoff' across universities is the most common error in Australia advising, and it also mis-sets which state boards are even eligible. | G2: https://www.sydney.edu.au/study/applying/how-to-apply/undergraduate/recognised-qualifications.html | H2: To be eligible for admission into one of our undergraduate degrees, you need to have completed one of the qualifications listed on this page. | I2: 14 September 2026 | J2: board: cbse, isc, state
A3: 2 | B3: Eligibility | C3: Check the course is CRICOS-registered and check the provider's visa prioritisation status | D3: 1 day | E3: Only a course registered on the Commonwealth Register of Institutions and Courses for Overseas Students (CRICOS) can support a subclass 500 visa, and the enrolment must be full time. Separately, since Ministerial Direction 111 (2024) and now MD 115, the provider's position against its New Overseas Student Commencement (NOSC) allocation determines how fast the visa is processed. Check the provider's status on the Department's Visa Prioritisation Status page on the day you lodge. | F3: Counselors treat provider choice as purely academic. Under MD 115 a provider that has passed 80 per cent of its allocation pushes the student to Priority 2, and one that has exceeded it by 15 per cent pushes them to Priority 3 - the difference between the Department starting work in 1-4 weeks and in 9-12 weeks. For a February start that gap alone can lose the intake. | G3: https://immi.homeaffairs.gov.au/visas/getting-a-visa/visa-processing-times/visa-processing-priorities/student-visa | H3: The Department will assign Priority 2 to applications associated with providers who have reached 80 per cent of their New Overseas Student Commencement (NOSC) allocation (their prioritisation threshold). | I3: 14 September 2026 (page last updated 10 November 2025)
A4: 3 | B4: Eligibility | C4: Separate the two English bars: the university's admission requirement and the visa's own requirement | D4: Test booking 2-6 weeks ahead; results 3-13 days | E4: These are two different tests of the same score and the university's is almost always the higher one. For the visa, tests sat on or after 7 August 2025 are assessed against a new table: IELTS Academic or IELTS General Training 6.0 overall, falling to 5.5 if the principal course is packaged with at least 10 weeks of ELICOS / a Foundation program / an eligible Pathway program, and 5.0 with at least 20 weeks of ELICOS. PTE Academic 50, TOEFL iBT 64 (on the pre-7-August-2025 table). Universities typically ask 6.5 overall with no band below 6.0 - the University of Melbourne Bachelor of Commerce is exactly that. | F4: Two traps. First, remote-proctored or at-home tests are not accepted at all for the visa, including IELTS Online - students who book the convenient version have to re-sit. Second, the Document Checklist Tool may say no English evidence is needed at lodgement, and counselors read that as an exemption; the Department can still ask for it at any point while the application is open. | G4: https://immi.homeaffairs.gov.au/visas/getting-a-visa/visa-listing/student-500 | H4: The Department of Home Affairs does not accept evidence from English language tests where an entire test is delivered online (also known as “remote-proctored” or “at-home”). | I4: 14 September 2026 (page last updated 1 July 2026)
A5: 4 | B5: Eligibility | C5: Pick the intake - February (Semester 1) or July (Semester 2) - and work backwards from that university's closing date | D5: Decision made 12-15 months before the start date | E5: The Australian year has two real intakes: Semester 1 starting late February/early March and Semester 2 starting late July/August. Published international closing dates for the February 2027 intake: University of Melbourne 30 November 2026; University of Sydney 1 December 2026; ANU 15 December 2026; UQ 30 November 2026. UNSW runs rolling offer rounds instead (published Term 1 2027 rounds included 14 May, 16 July, 20 August and 24 September 2026). UWA publishes country-banded dates - for 2026 Semester 1 most countries closed 19 January 2026. | F5: Treating the university closing date as the planning deadline. It is the last date to apply, not the date to aim for: an application lodged on the closing date leaves no room for the offer, the deposit, the CoE and a 40-71 day visa decision before a late-February start. The counselor's working deadline for a February intake is September of the preceding year, not November or December. | G5: https://study.unimelb.edu.au/find/courses/undergraduate/bachelor-of-commerce/ | H5: Direct international applications close: start-year intake 2027 (Semester 1/February-March) 30 November 2026. | I5: 13 September 2026 (verified in the Australia dataset)
A6: 5 | B6: Application | C6: Apply directly to the universities (or through an authorised agent) - there is no national portal | D6: 2-4 weeks to assemble; submit 12-14 months before the start date | E6: Unlike UCAS or Studielink, Australia has no single undergraduate portal for international applicants. Each university runs its own: Melbourne's application portal, apply.uq.edu.au, the UNSW Applicant Portal, ANU direct (AUD 150 per application), Monash direct (AUD 125 applicant fee or a waiver code), Adelaide University via StudyLink. The state TAC systems (VTAC, UAC, QTAC) are only for students completing an Australian Year 12 or, in some states, the IB in Australia - an Indian Standard XII student applies direct or through an authorised agent. Upload Standard XI and XII marksheets, the school-leaving certificate and the English test report. | F6: Applying to one university only. Because the offer -> deposit -> CoE -> visa chain is serial and each link can slip, a single offer is a single point of failure; and unlike the UK there is no clearing mechanism. Also: some universities require applicants from specified countries to apply through an authorised agent, so a direct application from those countries is simply not processed. | G6: https://study.unimelb.edu.au/find/courses/undergraduate/bachelor-of-commerce/ | H6: Direct online application via the University of Melbourne application portal for both intakes; applicants from certain countries must apply through an authorised education agent. | I6: 13 September 2026 (verified in the Australia dataset)
A7: 6 | B7: Application | C7: Receive the offer - and read whether it is conditional or unconditional | D7: 2-8 weeks after a complete application; UNSW and Monash assess in rounds or year-round | E7: Australian universities issue a Letter of Offer, usually conditional on final Standard XII results, an English test score, or both. The offer letter states the tuition deposit required, the OSHC arrangement and the acceptance deadline. A conditional offer cannot become a CoE - conditions must be cleared first. | F7: Waiting on a conditional offer through the CBSE results window. CBSE Class XII results land in May, which is comfortably in time for a July intake but irrelevant for February - a February applicant is applying with the previous year's completed results, so any condition left open is usually an English score, and that is fixable in weeks if the counselor catches it in the offer letter rather than in December. | G7: https://immi.homeaffairs.gov.au/visas/getting-a-visa/visa-listing/student-500 | H7: Provide a Confirmation of Enrolment (CoE) in a full time course registered on the Commonwealth Register of Institutions and courses for Overseas Students (CRICOS) for all intended courses. | I7: 14 September 2026 (page last updated 1 July 2026)
A8: 7 | B8: Application | C8: Accept the offer, pay the tuition deposit and arrange OSHC - this is what produces the CoE | D8: 1-3 weeks from payment to CoE issue | E8: Acceptance plus a tuition deposit (commonly one semester's fees) plus an OSHC policy triggers the university to issue an electronic Confirmation of Enrolment (eCoE) through PRISMS. The eCoE is the gating document for the whole visa: no CoE, no valid subclass 500 application. The university will normally put the OSHC provider, policy dates and policy number on the CoE itself. | F8: Two failure modes. The CoE must still be valid on the day the Department decides, not just on the day of lodgement - if the student defers or the university cancels enrolment mid-processing, the application dies unless a new CoE is attached in ImmiAccount. And if OSHC is not in the application at all, the Department says outright it will refuse rather than ask. | G8: https://immi.homeaffairs.gov.au/visas/getting-a-visa/visa-listing/student-500 | H8: Your CoE must be valid at time of lodgement and when we decide your visa application. A CoE is no longer valid if it is cancelled or the course is complete. | I8: 14 September 2026 (page last updated 1 July 2026)
A9: 8 | B9: Money | C9: Build the financial capacity file: AUD 29,710 living costs + 12 months course fees + AUD 2,000 travel | D9: Funds must have a visible 3-6 month history; assembling and documenting takes 4-8 weeks | E9: The 12-month living cost figure for a student is AUD 29,710, plus AUD 10,394 for an accompanying partner and AUD 4,449 per accompanying child. To that add the first 12 months of course fees (total fee divided by course years, less anything already paid and receipted) and travel costs - AUD 2,000 for an applicant outside Australia other than Africa. For a Group of Eight commerce degree at roughly AUD 56,000 a year, the declared requirement lands near AUD 87,700 before any deposit is deducted. Evidence can be bank deposits, a government or bank education loan, or a scholarship. | F9: A single-day bank balance certificate. The Department says explicitly that this does not show how the funds were accumulated - it wants transaction history, salary credits, growth patterns, or for a loan, evidence of disbursement. The second trap is the figure itself: Home Affairs set AUD 29,710 from 10 May 2024, replacing AUD 24,505, which had itself replaced a lower figure months earlier - and agents still quote the older numbers. AUD 29,710 is current on the Home Affairs page as last updated 1 July 2026, but it has moved twice in three years, so re-check it every cycle. | G9: https://immi.homeaffairs.gov.au/visas/getting-a-visa/visa-listing/student-500 | H9: 12-month living costs are for: students - AUD29,710; partners coming with you - AUD10,394; a child coming with you - AUD4,449. | I9: 14 September 2026 (page last updated 1 July 2026) | J9: passport: b
A10: 9 | B10: Money | C10: Or use the annual income route: AUD 87,856 parental/partner income (AUD 102,500 with family) | D10: Same cycle as the funds route; needs a 12-month-old-or-newer tax assessment | E10: Instead of showing accumulated funds, the applicant can show that a parent or partner (not travelling with them) had a personal annual income of at least AUD 87,856 in the 12 months before applying, or AUD 102,500 if family members are coming too. Both parents' incomes can be combined. The evidence must be official government documentation such as an Indian income tax assessment less than 12 months old. | F10: Submitting bank statements or an employer letter for this route - the Department rejects both by name for the income test. Also note the threshold has been raised: Home Affairs' own archived guidance stated AUD 60,000 (AUD 70,000 with family), and that pair is still quoted in circulating summaries. Building a file to the stale figure means building one that does not meet the test. | G10: https://immi.homeaffairs.gov.au/visas/getting-a-visa/visa-listing/student-500 | H10: Alternatively, you can give evidence that your parents or your partner had a personal annual income of at least AUD87,856 in the 12 months before you apply. If you bring family members, your parents’ or partner’s income must be at least AUD102,500 in the 12 months before you apply. | I10: 14 September 2026 (page last updated 1 July 2026) | J10: passport: b
A11: 10 | B11: Money | C11: Buy OSHC for the whole visa period, not the course period | D11: Same day online, or bundled by the university at offer acceptance | E11: Overseas Student Health Cover from an approved Australian insurer (ahm, Allianz Care/Peoplecare, Bupa, CBHS International, Medibank, nib) is compulsory for the entire stay. Proof of a paid policy must be in the application. There is no government-set price - it varies by insurer and policy length - so counselors should price it per insurer rather than quoting a number. Students from Norway, Sweden and Belgium are the only exceptions. | F11: Buying OSHC to the course end date. The visa grant period is longer than the course (see the length-of-stay step), and Home Affairs will only grant to the OSHC expiry date - and the visa end date cannot be changed once granted. The other trap is the start date: if the student flies in before semester, OSHC must start on the arrival date, not the course start date, or they can be refused entry. | G11: https://immi.homeaffairs.gov.au/visas/getting-a-visa/visa-listing/student-500 | H11: If you don’t provide your OSHC in your application form, we will refuse your visa application. | I11: 14 September 2026 (page last updated 1 July 2026) | J11: passport: b
A12: 11 | B12: Money | C12: Budget the visa application charge: AUD 2,500 from 1 July 2026 | D12: Paid at the moment of lodgement | E12: The Student visa application charge rose from AUD 2,000 to AUD 2,500 on 1 July 2026 for the primary applicant, after rising from AUD 710 to AUD 1,600 on 1 July 2024 and to AUD 2,000 in 2025. Independent ELICOS and non-award applicants are exempt from the increase and stay on the lower charge with annual CPI indexation. There is a separate charge for each accompanying family member. ASEAN, Pacific Island and Timor-Leste passport holders keep the lower concessional charge - Indian passport holders do not, and pay the full AUD 2,500. The charge is non-refundable if the visa is refused. | F12: Quoting the AUD 1,600 figure, which is now two increases out of date, and budgeting on the day of application rather than the day the Department receives it. Home Affairs states that if the price rises between lodging and receipt, the new charge is payable - and an application with an underpaid charge is not valid. | G12: https://www.studyaustralia.gov.au/en/tools-and-resources/news/student-visa-application-charge-increase | H12: The Student VAC increased from AUD $2,000 to AUD $2,500 from 1 July 2026. | I12: 14 September 2026 (Study Australia news item dated 3 July 2026) | J12: passport: b
A13: 12 | B13: Visa | C13: Create an ImmiAccount and run the Document Checklist Tool for an Indian passport and the chosen provider | D13: 1 day | E13: The subclass 500 is lodged online only, through ImmiAccount. Before lodging, run the Document Checklist Tool with the student's country of passport and their specific education provider - the checklist is provider-sensitive, because the required evidence level varies with the provider's and country's assessed risk. Re-run it immediately before submitting; Home Affairs updates it on 31 March and 30 September each year. | F13: Running the checklist once, months early, and lodging against a list that has since changed - or running it with 'I have not decided on a provider yet', which produces a generic and usually heavier list. The checklist output is also read as permission to omit things: it is not, and the Department can request anything at any point. | G13: https://immi.homeaffairs.gov.au/visas/getting-a-visa/visa-listing/student-500 | H13: Re-check the document checklist based on the country of passport and education provider just before you submit your application to be sure you have used the most current list. | I13: 14 September 2026 (page last updated 1 July 2026) | J13: passport: b
A14: 13 | B14: Visa | C14: Draft the Genuine Student (GS) answers - four questions, 150 words each, inside the form | D14: 2-4 weeks of drafting and evidence-gathering; do not leave it to the week of lodgement | E14: The Genuine Student requirement replaced the Genuine Temporary Entrant (GTE) test for applications lodged on or after 23 March 2024. It is not a personal statement attached as a PDF - it is four questions answered in the online form itself: (1) the applicant's current circumstances, including ties to family, community, employment and economic circumstances; (2) why this course, in Australia, with this particular provider, and what they understand about the course and about living in Australia; (3) how completing the course will benefit them; (4) any other relevant information. There is a fifth question for applicants who have held a student visa before or are applying onshore from a non-student visa. All answers in English, 150 words each, with supporting documents attached separately in ImmiAccount. | F14: Writing a GTE-style 'I will return home' essay. GS explicitly does not penalise a future intention to seek permanent residence - the Department says so in terms - so the old strategy of protesting non-migration intent wastes words. The second trap: Home Affairs states it prefers answers in the form over an attached statement, and that it gives more weight to statements supported by evidence. Unevidenced assertions about family business income, job offers or salary expectations are the commonest weak point in Indian files. | G14: https://immi.homeaffairs.gov.au/visas/getting-a-visa/visa-listing/student-500/genuine-student-requirement | H14: The GS requirement recognises that genuine students may develop skills Australia needs and may later choose to apply for permanent residence. Future intentions of this kind do not count against an applicant under GS. | I14: 14 September 2026 (page last updated 13 January 2026) | J14: passport: b
A15: 14 | B15: Visa | C15: Assemble the GS evidence pack: previous study, employment, home-country ties, economic circumstances | D15: 3-6 weeks running in parallel with the funds file | E15: Home Affairs names the evidence categories it wants: academic transcripts and certificates of attainment with provider names and study lengths; any previous study in Australia including reasons for changing course or provider and explanations of study gaps longer than 2 months; current employment details with a contactable referee; the nature of family, community and employment ties in India, plus reasons for not studying a similar course at home; and economic circumstances - 12 months of employment or business documents, income tax returns or bank statements, and any post-study employment offers with salary. | F15: Skipping the 'why not study this in India' answer. For an Indian student choosing a commerce or computer science degree that exists at home, this is the single question that most often decides the file, and it is the one most GS drafts leave implicit. Study gaps over two months and any prior visa refusal - to Australia or anywhere - must also be addressed head-on; immigration history is an explicit GS assessment factor. | G15: https://immi.homeaffairs.gov.au/visas/getting-a-visa/visa-listing/student-500/genuine-student-requirement | H15: the nature of the applicant’s personal ties e.g. family, community and employment. They must give reasons for not studying in their home country if a similar course is available. | I15: 14 September 2026 (page last updated 13 January 2026) | J15: passport: b
A16: 15 | B16: Visa | C16: Complete health examinations - before lodging if possible | D16: 1-3 weeks for appointment and clinic upload; longer if a chest X-ray needs review | E16: Applicants can complete health examinations before lodging (via My Health Declarations, which generates a HAP ID) or wait for the Department to request them after lodgement, in which case the medical referral letter and HAP ID appear in ImmiAccount. Examinations must be done at a panel clinic. Doing them upfront removes one request-and-wait cycle from processing. | F16: Leaving health checks until the Department asks. For a February intake lodged in October or November, a post-lodgement health request plus clinic backlog plus results upload can add three to five weeks at exactly the wrong point. India is also a higher-TB-prevalence country, so a chest X-ray finding that needs specialist review is not rare, and that review has no fixed timeline. | G16: https://immi.homeaffairs.gov.au/visas/getting-a-visa/visa-listing/student-500 | H16: You might need to have health examinations. You can complete them before you apply. | I16: 14 September 2026 (page last updated 1 July 2026) | J16: passport: b
A17: 16 | B17: Visa | C17: Time the lodgement date against the provider's prioritisation year - it resets on 15 November | D17: A single scheduling decision, worth weeks of processing time | E17: Ministerial Direction 115 measures a provider against its indicative allocation of New Overseas Student Commencements on a year that runs 15 November to 14 November. Applications lodged from 15 November 2026 to 14 November 2027 are prioritised against the provider's 2027 allocation, which starts fresh. MD 115 also states plainly that the allocation is not a cap on visas granted and not a suspension of processing - it only sets the order in which applications are picked up. Priority 1 is a provider below 80 per cent of allocation, Priority 2 is between 80 and 115 per cent, Priority 3 is above 115 per cent. | F17: Lodging in September or October against an allocation that is already spent, when waiting to 15 November would have reset the provider to Priority 1 for the following year. For a February 2027 start this is the sharpest lever a counselor has: a mid-November lodgement can be picked up in 1-4 weeks where an October one sits 9-12 weeks. The mirror-image trap is misreading the allocation as a cap and telling a student the university is 'full' - it is not; it is a processing queue. | G17: https://immi.homeaffairs.gov.au/support-subsite/files/ministerial-direction-115.pdf | H17: For a provider's prioritisation threshold for the calendar year 2026, offshore student visa applications received on or after 15 November 2025 and up to and including 14 November 2026 will be prioritised with respect to the 2026 calendar year. | I17: 14 September 2026 (Ministerial Direction 115, commenced 14 November 2025) | J17: passport: b
A18: 17 | B18: Visa | C18: Lodge the subclass 500 in ImmiAccount, complete, and pay AUD 2,500 | D18: Lodgement day; aim to lodge 4-5 months before the course start date | E18: Attach everything at lodgement: passport bio page, CoE(s), GS answers and evidence, financial capacity evidence, OSHC proof, English test report (both certificate and report for LANGUAGECERT), identity and name-change documents, and a polio vaccination certificate where the applicant has spent time in an at-risk country. Maximum 60 attachments. Family members must be declared on the application even if they are not travelling. Then pay the charge - an unpaid or underpaid charge makes the application invalid. | F18: Lodging a skeleton application intending to 'add documents later'. The Department states it may finalise the application on what was provided at lodgement - a thin file can be refused without a request for more information, and a refusal then has to be declared in every future visa application anywhere. Specifically, missing financial evidence that the checklist required is grounds for refusal without further contact. | G18: https://immi.homeaffairs.gov.au/visas/getting-a-visa/visa-listing/student-500 | H18: If you are required to attach evidence of your financial capacity to your ImmiAccount when you submit your application, you must do so. If you don’t give this evidence, we may refuse your application without asking you for more information. | I18: 14 September 2026 (page last updated 1 July 2026) | J18: passport: b
A19: 18 | B19: Visa | C19: Give biometrics within 14 days of the request | D19: Request usually arrives immediately after submission; appointment within 1-2 weeks | E19: Most applicants are told immediately after submitting whether biometrics are required. The request arrives by letter and appears in ImmiAccount, and the applicant is given 14 days to comply, at an Australian Biometric Collection Centre. Biometrics must be provided before travelling to Australia. | F19: Treating the 14 days as elastic. Appointment availability in Indian metros tightens sharply in the October-December offshore peak, and the student who books in week two can find nothing inside the window. This is a small step that quietly stalls files. | G19: https://immi.homeaffairs.gov.au/visas/getting-a-visa/visa-listing/student-500 | H19: You will be given 14 days to provide biometrics so it is important to arrange an appointment quickly using the instructions in the request letter. | I19: 14 September 2026 (page last updated 1 July 2026) | J19: passport: b
A20: 19 | B20: Visa | C20: Processing - understand both the published time and the Ministerial Direction queue | D20: Higher Education sector: 50% within 19 days, 75% within 40 days, 90% within 71 days | E20: Home Affairs publishes global processing times by sector, not by country - there is no India-specific published subclass 500 time. For the Higher Education sector, applications decided in the month ending 31 July 2026 took 10 days at the 25th percentile, 19 days at the 50th, 40 days at the 75th and 71 days at the 90th (figures updated 4 September 2026). Separately, offshore applications lodged on or after 14 November 2025 are queued under Ministerial Direction 115, under which the Department aims to commence processing Priority 1 within 1-4 weeks, Priority 2 within 5-8 weeks and Priority 3 within 9-12 weeks of lodgement. | F20: Planning on the median. The 90th-percentile figure - 71 days for higher education, and 7 months for VET - is the number that decides whether a student makes the intake. Add MD 115's commencement lag on top: a Priority 3 application is not even picked up for 9-12 weeks, so the realistic worst case is a decision four to five months after lodgement. Counselors also need to know the priority level is fixed at lodgement day and never improves, so lodging while a provider is still below its threshold is worth real money. | G20: https://immi.homeaffairs.gov.au/visas/getting-a-visa/visa-processing-times/global-visa-processing-times | H20: Higher Education Sector — 25%: 10 Days; 50%: 19 Days; 75%: 40 Days; 90%: 71 Days (Updated 04 September 2026, period ending 31 July 2026). | I20: 14 September 2026 | J20: passport: b
... A22: 21 | B22: Arrival | C22: Travel - not before the OSHC start date, and not on a ticket booked before the grant | D22: Arrive 1-4 weeks before semester starts | E22: Students normally arrive one to four weeks before semester for orientation and housing. The OSHC policy must already have begun on the day of arrival, not on the day the course starts. Home Affairs advises against booking travel before the visa is finalised. | F22: Booking flights on a conditional offer, or landing a week before the OSHC policy begins. Home Affairs warns the student may be refused entry at the border if they cannot show health insurance is in place on arrival - a February-intake student who flew in mid-January on a policy dated from 1 March is the classic case. | G22: https://immi.homeaffairs.gov.au/visas/getting-a-visa/visa-listing/student-500 | H22: You may be refused entry to Australia if you cannot prove you have health insurance in place when you arrive. | I22: 14 September 2026 (page last updated 1 July 2026) | J22: passport: b
A23: 22 | B23: Arrival | C23: Enrol, attend orientation, and start meeting condition 8202 from day one | D23: Orientation week, then continuous for the length of the course | E23: There is no municipal registration step in Australia - nothing equivalent to Germany's Anmeldung or a residence-permit conversion. The visa granted offshore is the residence right. What replaces it is ongoing compliance: enrol in and maintain a full-time CRICOS-registered load, meet course progress and attendance requirements (condition 8202), keep OSHC current (8501), and keep the address updated with the provider. Practical first-fortnight admin: Tax File Number, an Australian bank account, a local SIM, and a student transport concession where the state offers one to international students. | F23: Dropping below a full-time load, or deferring after arrival, without realising it breaches 8202 and can lead to visa cancellation. Students also cannot work at all before the course begins - condition 8105 does not switch on until the course starts, and an early part-time job is a breach. | G23: https://immi.homeaffairs.gov.au/visas/getting-a-visa/visa-listing/student-500 | H23: Student visa holders and their family members cannot work in Australia before the student starts their course. | I23: 14 September 2026 (page last updated 1 July 2026)
A24: 23 | B24: Arrival | C24: Plan the post-study step: Temporary Graduate visa (subclass 485), charge AUD 5,750 from 1 July 2026 | D24: Apply after completing the degree, while still onshore and holding a student visa | E24: The subclass 485 is the standard post-study work route after an Australian degree. Its application charge rose from AUD 4,600 to AUD 5,750 on 1 July 2026, in the same round that took the student charge to AUD 2,500. Holders have unlimited work rights. The concession for Pacific Island and Timor-Leste applicants continues; Indian passport holders pay the full charge. | F24: Selling the 485 at the counselling stage as though it were automatic. It has its own age, English, qualification and time-limit criteria that must be checked in the year the student actually graduates, and the charge has now more than doubled in two years - a student budgeting in 2026 for a 2029 graduation should assume it will rise again. | G24: https://www.studyaustralia.gov.au/en/tools-and-resources/news/student-visa-application-charge-increase | H24: The Temporary Graduate Visa application charge increased from AUD $4,600 to AUD $5,750 from 1 July 2026. | I24: 14 September 2026 (Study Australia news item dated 3 July 2026) | J24: passport: b

Sheet Institutions
A1: Fill the two yellow columns once per university. Both apply to every programme at that university.
A2: University | B2: Programmes in the file | C2: Campus city | D2: Homepage | E2: Currently typed as
A3: Example: University of Melbourne | B3: 6 | C3: Melbourne | D3: https://www.unimelb.edu.au/ | E3: Go8 / Top Research
A4: University of Melbourne | B4: 6 | E4: Go8 / Top Research
A5: University of Sydney | B5: 6 | E5: Go8 / Top Research
A6: UNSW Sydney | B6: 6 | E6: Go8 / Top Research
A7: Australian National University (ANU) | B7: 6 | E7: Go8 / Top Research
A8: Monash University | B8: 6 | E8: Go8 / Top Research
A9: University of Queensland (UQ) | B9: 6 | E9: Go8 / Top Research
A10: Adelaide University (merged University of Adelaide + UniSA; sheet listed University of Adelaide) | B10: 5 | E10: Go8 / Top Research
A11: University of Western Australia (UWA) | B11: 4 | E11: Go8 / Top Research
A13: Total programmes | B13: =SUM(B4:B11)
A14: Cities still to fill | B14: =COUNTBLANK(C4:C11)
A15: Homepages still to fill | B15: =COUNTBLANK(D4:D11)

Sheet Coverage
A1: Field
A2: Field | B2: Filled in Australia | C2: Out of 45 | D2: Germany fills | E2: Out of 80 | F2: Read
A3: record_id | B3: =COUNTIF(Programmes!A2:A46,"?*") | C3: 45 | D3: 80 | E3: 80 | F3: Complete
A4: institution | B4: =COUNTIF(Programmes!B2:B46,"?*") | C4: 45 | D4: 80 | E4: 80 | F4: Complete
A5: instType | B5: =COUNTIF(Programmes!G2:G46,"?*") | C5: 45 | D5: 80 | E5: 80 | F5: Complete
A6: city | B6: =COUNTIF(Programmes!C2:C46,"?*") | C6: 45 | D6: 80 | E6: 80 | F6: Complete
A7: instUrl | B7: 0 | C7: 45 | D7: 80 | E7: 80 | F7: Empty here, filled in Germany
A8: programme | B8: =COUNTIF(Programmes!D2:D46,"?*") | C8: 45 | D8: 80 | E8: 80 | F8: Complete
A9: degree | B9: =COUNTIF(Programmes!E2:E46,"?*") | C9: 45 | D9: 80 | E9: 80 | F9: Complete
A10: url | B10: =COUNTIF(Programmes!F2:F46,"?*") | C10: 45 | D10: 80 | E10: 80 | F10: Complete
A11: language | B11: =COUNTIF(Programmes!H2:H46,"?*") | C11: 45 | D11: 80 | E11: 80 | F11: Complete
A12: years | B12: =COUNTIF(Programmes!I2:I46,"?*") | C12: 45 | D12: 80 | E12: 80 | F12: Complete
A13: entry | B13: =COUNTIF(Programmes!J2:J46,"?*") | C13: 45 | D13: 80 | E13: 80 | F13: 17 record(s) blank
A14: ib | B14: =COUNTIF(Programmes!K2:K46,"?*") | C14: 45 | D14: 80 | E14: 80 | F14: Complete
A15: alevel | B15: =COUNTIF(Programmes!L2:L46,"?*") | C15: 45 | D15: 80 | E15: 80 | F15: Complete
A16: cbse | B16: =COUNTIF(Programmes!M2:M46,"?*") | C16: 45 | D16: 80 | E16: 80 | F16: Complete
A17: isc | B17: =COUNTIF(Programmes!N2:N46,"?*") | C17: 45 | D17: 80 | E17: 80 | F17: Complete
A18: other | B18: =COUNTIF(Programmes!O2:O46,"?*") | C18: 45 | D18: 80 | E18: 80 | F18: Complete
A19: english | B19: =COUNTIF(Programmes!P2:P46,"?*") | C19: 45 | D19: 80 | E19: 80 | F19: Complete
A20: selection | B20: =COUNTIF(Programmes!Q2:Q46,"?*") | C20: 45 | D20: 80 | E20: 80 | F20: Complete
A21: deadline | B21: =COUNTIF(Programmes!R2:R46,"?*") | C21: 45 | D21: 79 | E21: 80 | F21: Complete
A22: feeEU | B22: 0 | C22: 45 | D22: 78 | E22: 80 | F22: Empty here, filled in Germany
A23: feeNonEU | B23: =COUNTIF(Programmes!S2:S46,"?*") | C23: 45 | D23: 79 | E23: 80 | F23: Complete
A24: liveLo | B24: 0 | C24: 45 | D24: 47 | E24: 80 | F24: Empty here, filled in Germany
A25: liveHi | B25: 0 | C25: 45 | D25: 47 | E25: 80 | F25: Empty here, filled in Germany
A26: scholarships | B26: =COUNTIF(Programmes!T2:T46,"?*") | C26: 45 | D26: 80 | E26: 80 | F26: Complete
A27: visa | B27: =COUNTIF(Programmes!U2:U46,"?*") | C27: 45 | D27: 80 | E27: 80 | F27: Complete
A28: apply | B28: =COUNTIF(Programmes!V2:V46,"?*") | C28: 45 | D28: 80 | E28: 80 | F28: Complete
A29: notes | B29: =COUNTIF(Programmes!W2:W46,"?*") | C29: 45 | D29: 73 | E29: 80 | F29: Complete
A30: verified_status | B30: =COUNTIF(Programmes!X2:X46,"?*") | C30: 45 | D30: 80 | E30: 80 | F30: Complete
A31: corrected_value_if_any | B31: =COUNTIF(Programmes!Y2:Y46,"?*") | C31: 45 | D31: 5 | E31: 80 | F31: Complete
A32: source_url_you_used | B32: =COUNTIF(Programmes!Z2:Z46,"?*") | C32: 45 | D32: 80 | E32: 80 | F32: Complete
A33: exact_quote | B33: =COUNTIF(Programmes!AA2:AA46,"?*") | C33: 45 | D33: 9 | E33: 80 | F33: Complete
A34: date_checked | B34: =COUNTIF(Programmes!AB2:AB46,"?*") | C34: 45 | D34: 80 | E34: 80 | F34: Complete
A35: link_works | B35: =COUNTIF(Programmes!AC2:AC46,"?*") | C35: 45 | D35: 10 | E35: 80 | F35: 11 record(s) blank
A36: checked_by | B36: =COUNTIF(Programmes!AD2:AD46,"?*") | C36: 45 | D36: 80 | E36: 80 | F36: Complete
A37: contact | B37: 0 | C37: 45 | D37: 80 | E37: 80 | F37: Empty here, filled in Germany
A38: documents_required | B38: =COUNTIF(Programmes!AE2:AE46,"?*") | C38: 45 | D38: 79 | E38: 80 | F38: Complete
A39: deadline_rounds | B39: =COUNTIF(Programmes!AF2:AF46,"?*") | C39: 45 | D39: 75 | E39: 80 | F39: Complete
A40: progression_routes | B40: 0 | C40: 45 | D40: 0 | E40: 80 | F40: Empty in both. Unused field
A41: us_diploma_gpa | B41: 0 | C41: 45 | D41: 60 | E41: 80 | F41: Empty here, filled in Germany
A42: accreditation | B42: 0 | C42: 45 | D42: 78 | E42: 80 | F42: Empty here, filled in Germany
A43: fee_year | B43: =COUNTIF(Programmes!AG2:AG46,"?*") | C43: 45 | D43: 0 | E43: 80 | F43: Complete
A44: application_fee | B44: =COUNTIF(Programmes!AH2:AH46,"?*") | C44: 45 | D44: 78 | E44: 80 | F44: Complete
A45: deadline_iso | B45: =COUNTIF(Programmes!AI2:AI46,"?*") | C45: 45 | D45: 33 | E45: 80 | F45: 22 record(s) blank
A46: india_entry | B46: =COUNTIF(Programmes!AJ2:AJ46,"?*") | C46: 45 | D46: 71 | E46: 80 | F46: Complete
